<?xml version="1.0" encoding="UTF-8" standalone="yes"?><bns:Component xmlns:xsi="http://www.w3.org/2001/XMLSchema-instance" xmlns:bns="http://api.platform.boomi.com/" folderFullPath="JERA Co., Inc./New HR - Interfaces /JUPITER_COMPANY/HR_Company_sending" componentId="72e31b52-d921-4119-8c00-5de67acdc399" version="1" name="final_attendance" type="profile.flatfile" createdDate="2021-02-02T01:09:54Z" createdBy="Daly.Fadhloun@avaxia-group.com" modifiedDate="2021-02-02T01:09:54Z" modifiedBy="Daly.Fadhloun@avaxia-group.com" deleted="false" currentVersion="true" folderName="HR_Company_sending" folderId="RjozNjk1MTI4" branchName="main" branchId="QjozMzg0ODI"><bns:encryptedValues/><bns:description></bns:description><bns:object><FlatFileProfile xmlns="" modelVersion="2" strict="true"><ProfileProperties><GeneralInfo fileType="delimited" useColumnHeaders="false"/><Options><DataOptions/><DelimitedOptions fileDelimiter="commadelimited" removeEscape="false" textQualifier="na"/></Options></ProfileProperties><DataElements><FlatFileRecord detectFormat="numberofcolumns" isNode="true" key="1" name="Record"><FlatFileElements isNode="true" key="2" name="Elements"><FlatFileElement dataType="character" enforceUnique="false" isMappable="true" isNode="true" key="3" mandatory="false" maxLength="0" minLength="0" name="4" useToIdentifyFormat="false" validateData="false"><DataFormat><ProfileCharacterFormat/></DataFormat></FlatFileElement><FlatFileElement dataType="character" enforceUnique="false" isMappable="true" isNode="true" key="4" mandatory="false" maxLength="0" minLength="0" name="sdate" useToIdentifyFormat="false" validateData="false"><DataFormat><ProfileCharacterFormat/></DataFormat></FlatFileElement><FlatFileElement dataType="character" enforceUnique="false" isMappable="true" isNode="true" key="5" mandatory="false" maxLength="0" minLength="0" name="edate" useToIdentifyFormat="false" validateData="false"><DataFormat><ProfileCharacterFormat/></DataFormat></FlatFileElement><FlatFileElement dataType="character" enforceUnique="false" isMappable="true" isNode="true" key="6" mandatory="false" maxLength="0" minLength="0" name="2401" useToIdentifyFormat="false" validateData="false"><DataFormat><ProfileCharacterFormat/></DataFormat></FlatFileElement><FlatFileElement dataType="character" enforceUnique="false" isMappable="true" isNode="true" key="7" mandatory="false" maxLength="0" minLength="0" name="2402" useToIdentifyFormat="false" validateData="false"><DataFormat><ProfileCharacterFormat/></DataFormat></FlatFileElement><FlatFileElement dataType="character" enforceUnique="false" isMappable="true" isNode="true" key="8" mandatory="false" maxLength="0" minLength="0" name="2403" useToIdentifyFormat="false" validateData="false"><DataFormat><ProfileCharacterFormat/></DataFormat></FlatFileElement><FlatFileElement dataType="character" enforceUnique="false" isMappable="true" isNode="true" key="9" mandatory="false" maxLength="0" minLength="0" name="2404" useToIdentifyFormat="false" validateData="false"><DataFormat><ProfileCharacterFormat/></DataFormat></FlatFileElement><FlatFileElement dataType="character" enforceUnique="false" isMappable="true" isNode="true" key="10" mandatory="false" maxLength="0" minLength="0" name="2405" useToIdentifyFormat="false" validateData="false"><DataFormat><ProfileCharacterFormat/></DataFormat></FlatFileElement><FlatFileElement dataType="character" enforceUnique="false" isMappable="true" isNode="true" key="11" mandatory="false" maxLength="0" minLength="0" name="2406" useToIdentifyFormat="false" validateData="false"><DataFormat><ProfileCharacterFormat/></DataFormat></FlatFileElement><FlatFileElement dataType="character" enforceUnique="false" isMappable="true" isNode="true" key="12" mandatory="false" maxLength="0" minLength="0" name="2407" useToIdentifyFormat="false" validateData="false"><DataFormat><ProfileCharacterFormat/></DataFormat></FlatFileElement><FlatFileElement dataType="character" enforceUnique="false" isMappable="true" isNode="true" key="13" mandatory="false" maxLength="0" minLength="0" name="2408" useToIdentifyFormat="false" validateData="false"><DataFormat><ProfileCharacterFormat/></DataFormat></FlatFileElement><FlatFileElement dataType="character" enforceUnique="false" isMappable="true" isNode="true" key="14" mandatory="false" maxLength="0" minLength="0" name="2411" useToIdentifyFormat="false" validateData="false"><DataFormat><ProfileCharacterFormat/></DataFormat></FlatFileElement><FlatFileElement dataType="character" enforceUnique="false" isMappable="true" isNode="true" key="15" mandatory="false" maxLength="0" minLength="0" name="2412" useToIdentifyFormat="false" validateData="false"><DataFormat><ProfileCharacterFormat/></DataFormat></FlatFileElement><FlatFileElement dataType="character" enforceUnique="false" isMappable="true" isNode="true" key="16" mandatory="false" maxLength="0" minLength="0" name="2413" useToIdentifyFormat="false" validateData="false"><DataFormat><ProfileCharacterFormat/></DataFormat></FlatFileElement><FlatFileElement dataType="character" enforceUnique="false" isMappable="true" isNode="true" key="17" mandatory="false" maxLength="0" minLength="0" name="2450" useToIdentifyFormat="false" validateData="false"><DataFormat><ProfileCharacterFormat/></DataFormat></FlatFileElement><FlatFileElement dataType="character" enforceUnique="false" isMappable="true" isNode="true" key="18" mandatory="false" maxLength="0" minLength="0" name="2501" useToIdentifyFormat="false" validateData="false"><DataFormat><ProfileCharacterFormat/></DataFormat></FlatFileElement><FlatFileElement dataType="character" enforceUnique="false" isMappable="true" isNode="true" key="19" mandatory="false" maxLength="0" minLength="0" name="2502" useToIdentifyFormat="false" validateData="false"><DataFormat><ProfileCharacterFormat/></DataFormat></FlatFileElement><FlatFileElement dataType="character" enforceUnique="false" isMappable="true" isNode="true" key="20" mandatory="false" maxLength="0" minLength="0" name="2503" useToIdentifyFormat="false" validateData="false"><DataFormat><ProfileCharacterFormat/></DataFormat></FlatFileElement><FlatFileElement dataType="character" enforceUnique="false" isMappable="true" isNode="true" key="21" mandatory="false" maxLength="0" minLength="0" name="2504" useToIdentifyFormat="false" validateData="false"><DataFormat><ProfileCharacterFormat/></DataFormat></FlatFileElement><FlatFileElement dataType="character" enforceUnique="false" isMappable="true" isNode="true" key="22" mandatory="false" maxLength="0" minLength="0" name="2505" useToIdentifyFormat="false" validateData="false"><DataFormat><ProfileCharacterFormat/></DataFormat></FlatFileElement><FlatFileElement dataType="character" enforceUnique="false" isMappable="true" isNode="true" key="23" mandatory="false" maxLength="0" minLength="0" name="2511" useToIdentifyFormat="false" validateData="false"><DataFormat><ProfileCharacterFormat/></DataFormat></FlatFileElement><FlatFileElement dataType="character" enforceUnique="false" isMappable="true" isNode="true" key="24" mandatory="false" maxLength="0" minLength="0" name="2512" useToIdentifyFormat="false" validateData="false"><DataFormat><ProfileCharacterFormat/></DataFormat></FlatFileElement><FlatFileElement dataType="character" enforceUnique="false" isMappable="true" isNode="true" key="25" mandatory="false" maxLength="0" minLength="0" name="2513" useToIdentifyFormat="false" validateData="false"><DataFormat><ProfileCharacterFormat/></DataFormat></FlatFileElement><FlatFileElement dataType="character" enforceUnique="false" isMappable="true" isNode="true" key="26" mandatory="false" maxLength="0" minLength="0" name="2514" useToIdentifyFormat="false" validateData="false"><DataFormat><ProfileCharacterFormat/></DataFormat></FlatFileElement><FlatFileElement dataType="character" enforceUnique="false" isMappable="true" isNode="true" key="27" mandatory="false" maxLength="0" minLength="0" name="2515" useToIdentifyFormat="false" validateData="false"><DataFormat><ProfileCharacterFormat/></DataFormat></FlatFileElement><FlatFileElement dataType="character" enforceUnique="false" isMappable="true" isNode="true" key="28" mandatory="false" maxLength="0" minLength="0" name="2516" useToIdentifyFormat="false" validateData="false"><DataFormat><ProfileCharacterFormat/></DataFormat></FlatFileElement><FlatFileElement dataType="character" enforceUnique="false" isMappable="true" isNode="true" key="29" mandatory="false" maxLength="0" minLength="0" name="2517" useToIdentifyFormat="false" validateData="false"><DataFormat><ProfileCharacterFormat/></DataFormat></FlatFileElement><FlatFileElement dataType="character" enforceUnique="false" isMappable="true" isNode="true" key="30" mandatory="false" maxLength="0" minLength="0" name="2518" useToIdentifyFormat="false" validateData="false"><DataFormat><ProfileCharacterFormat/></DataFormat></FlatFileElement><FlatFileElement dataType="character" enforceUnique="false" isMappable="true" isNode="true" key="31" mandatory="false" maxLength="0" minLength="0" name="2519" useToIdentifyFormat="false" validateData="false"><DataFormat><ProfileCharacterFormat/></DataFormat></FlatFileElement><FlatFileElement dataType="character" enforceUnique="false" isMappable="true" isNode="true" key="32" mandatory="false" maxLength="0" minLength="0" name="2521" useToIdentifyFormat="false" validateData="false"><DataFormat><ProfileCharacterFormat/></DataFormat></FlatFileElement><FlatFileElement dataType="character" enforceUnique="false" isMappable="true" isNode="true" key="33" mandatory="false" maxLength="0" minLength="0" name="2522" useToIdentifyFormat="false" validateData="false"><DataFormat><ProfileCharacterFormat/></DataFormat></FlatFileElement><FlatFileElement dataType="character" enforceUnique="false" isMappable="true" isNode="true" key="34" mandatory="false" maxLength="0" minLength="0" name="2523" useToIdentifyFormat="false" validateData="false"><DataFormat><ProfileCharacterFormat/></DataFormat></FlatFileElement><FlatFileElement dataType="character" enforceUnique="false" isMappable="true" isNode="true" key="35" mandatory="false" maxLength="0" minLength="0" name="2524" useToIdentifyFormat="false" validateData="false"><DataFormat><ProfileCharacterFormat/></DataFormat></FlatFileElement><FlatFileElement dataType="character" enforceUnique="false" isMappable="true" isNode="true" key="36" mandatory="false" maxLength="0" minLength="0" name="2525" useToIdentifyFormat="false" validateData="false"><DataFormat><ProfileCharacterFormat/></DataFormat></FlatFileElement><FlatFileElement dataType="character" enforceUnique="false" isMappable="true" isNode="true" key="37" mandatory="false" maxLength="0" minLength="0" name="2526" useToIdentifyFormat="false" validateData="false"><DataFormat><ProfileCharacterFormat/></DataFormat></FlatFileElement><FlatFileElement dataType="character" enforceUnique="false" isMappable="true" isNode="true" key="38" mandatory="false" maxLength="0" minLength="0" name="2527" useToIdentifyFormat="false" validateData="false"><DataFormat><ProfileCharacterFormat/></DataFormat></FlatFileElement><FlatFileElement dataType="character" enforceUnique="false" isMappable="true" isNode="true" key="39" mandatory="false" maxLength="0" minLength="0" name="2528" useToIdentifyFormat="false" validateData="false"><DataFormat><ProfileCharacterFormat/></DataFormat></FlatFileElement><FlatFileElement dataType="character" enforceUnique="false" isMappable="true" isNode="true" key="40" mandatory="false" maxLength="0" minLength="0" name="2529" useToIdentifyFormat="false" validateData="false"><DataFormat><ProfileCharacterFormat/></DataFormat></FlatFileElement><FlatFileElement dataType="character" enforceUnique="false" isMappable="true" isNode="true" key="41" mandatory="false" maxLength="0" minLength="0" name="2530" useToIdentifyFormat="false" validateData="false"><DataFormat><ProfileCharacterFormat/></DataFormat></FlatFileElement><FlatFileElement dataType="character" enforceUnique="false" isMappable="true" isNode="true" key="42" mandatory="false" maxLength="0" minLength="0" name="2531" useToIdentifyFormat="false" validateData="false"><DataFormat><ProfileCharacterFormat/></DataFormat></FlatFileElement><FlatFileElement dataType="character" enforceUnique="false" isMappable="true" isNode="true" key="43" mandatory="false" maxLength="0" minLength="0" name="2532" useToIdentifyFormat="false" validateData="false"><DataFormat><ProfileCharacterFormat/></DataFormat></FlatFileElement><FlatFileElement dataType="character" enforceUnique="false" isMappable="true" isNode="true" key="44" mandatory="false" maxLength="0" minLength="0" name="2533" useToIdentifyFormat="false" validateData="false"><DataFormat><ProfileCharacterFormat/></DataFormat></FlatFileElement><FlatFileElement dataType="character" enforceUnique="false" isMappable="true" isNode="true" key="45" mandatory="false" maxLength="0" minLength="0" name="2534" useToIdentifyFormat="false" validateData="false"><DataFormat><ProfileCharacterFormat/></DataFormat></FlatFileElement><FlatFileElement dataType="character" enforceUnique="false" isMappable="true" isNode="true" key="46" mandatory="false" maxLength="0" minLength="0" name="2535" useToIdentifyFormat="false" validateData="false"><DataFormat><ProfileCharacterFormat/></DataFormat></FlatFileElement><FlatFileElement dataType="character" enforceUnique="false" isMappable="true" isNode="true" key="47" mandatory="false" maxLength="0" minLength="0" name="2536" useToIdentifyFormat="false" validateData="false"><DataFormat><ProfileCharacterFormat/></DataFormat></FlatFileElement><FlatFileElement dataType="character" enforceUnique="false" isMappable="true" isNode="true" key="48" mandatory="false" maxLength="0" minLength="0" name="2541" useToIdentifyFormat="false" validateData="false"><DataFormat><ProfileCharacterFormat/></DataFormat></FlatFileElement><FlatFileElement dataType="character" enforceUnique="false" isMappable="true" isNode="true" key="49" mandatory="false" maxLength="0" minLength="0" name="2542" useToIdentifyFormat="false" validateData="false"><DataFormat><ProfileCharacterFormat/></DataFormat></FlatFileElement><FlatFileElement dataType="character" enforceUnique="false" isMappable="true" isNode="true" key="50" mandatory="false" maxLength="0" minLength="0" name="2543" useToIdentifyFormat="false" validateData="false"><DataFormat><ProfileCharacterFormat/></DataFormat></FlatFileElement><FlatFileElement dataType="character" enforceUnique="false" isMappable="true" isNode="true" key="51" mandatory="false" maxLength="0" minLength="0" name="2544" useToIdentifyFormat="false" validateData="false"><DataFormat><ProfileCharacterFormat/></DataFormat></FlatFileElement><FlatFileElement dataType="character" enforceUnique="false" isMappable="true" isNode="true" key="52" mandatory="false" maxLength="0" minLength="0" name="2546" useToIdentifyFormat="false" validateData="false"><DataFormat><ProfileCharacterFormat/></DataFormat></FlatFileElement><FlatFileElement dataType="character" enforceUnique="false" isMappable="true" isNode="true" key="53" mandatory="false" maxLength="0" minLength="0" name="2547" useToIdentifyFormat="false" validateData="false"><DataFormat><ProfileCharacterFormat/></DataFormat></FlatFileElement><FlatFileElement dataType="character" enforceUnique="false" isMappable="true" isNode="true" key="54" mandatory="false" maxLength="0" minLength="0" name="2548" useToIdentifyFormat="false" validateData="false"><DataFormat><ProfileCharacterFormat/></DataFormat></FlatFileElement><FlatFileElement dataType="character" enforceUnique="false" isMappable="true" isNode="true" key="55" mandatory="false" maxLength="0" minLength="0" name="2549" useToIdentifyFormat="false" validateData="false"><DataFormat><ProfileCharacterFormat/></DataFormat></FlatFileElement><FlatFileElement dataType="character" enforceUnique="false" isMappable="true" isNode="true" key="56" mandatory="false" maxLength="0" minLength="0" name="2551" useToIdentifyFormat="false" validateData="false"><DataFormat><ProfileCharacterFormat/></DataFormat></FlatFileElement><FlatFileElement dataType="character" enforceUnique="false" isMappable="true" isNode="true" key="57" mandatory="false" maxLength="0" minLength="0" name="2552" useToIdentifyFormat="false" validateData="false"><DataFormat><ProfileCharacterFormat/></DataFormat></FlatFileElement><FlatFileElement dataType="character" enforceUnique="false" isMappable="true" isNode="true" key="58" mandatory="false" maxLength="0" minLength="0" name="2553" useToIdentifyFormat="false" validateData="false"><DataFormat><ProfileCharacterFormat/></DataFormat></FlatFileElement><FlatFileElement dataType="character" enforceUnique="false" isMappable="true" isNode="true" key="59" mandatory="false" maxLength="0" minLength="0" name="2554" useToIdentifyFormat="false" validateData="false"><DataFormat><ProfileCharacterFormat/></DataFormat></FlatFileElement><FlatFileElement dataType="character" enforceUnique="false" isMappable="true" isNode="true" key="60" mandatory="false" maxLength="0" minLength="0" name="2416" useToIdentifyFormat="false" validateData="false"><DataFormat><ProfileCharacterFormat/></DataFormat></FlatFileElement><FlatFileElement dataType="character" enforceUnique="false" isMappable="true" isNode="true" key="61" mandatory="false" maxLength="0" minLength="0" name="2417" useToIdentifyFormat="false" validateData="false"><DataFormat><ProfileCharacterFormat/></DataFormat></FlatFileElement><FlatFileElement dataType="character" enforceUnique="false" isMappable="true" isNode="true" key="62" mandatory="false" maxLength="0" minLength="0" name="2418" useToIdentifyFormat="false" validateData="false"><DataFormat><ProfileCharacterFormat/></DataFormat></FlatFileElement><FlatFileElement dataType="character" enforceUnique="false" isMappable="true" isNode="true" key="63" mandatory="false" maxLength="0" minLength="0" name="2419" useToIdentifyFormat="false" validateData="false"><DataFormat><ProfileCharacterFormat/></DataFormat></FlatFileElement><FlatFileElement dataType="character" enforceUnique="false" isMappable="true" isNode="true" key="64" mandatory="false" maxLength="0" minLength="0" name="2420" useToIdentifyFormat="false" validateData="false"><DataFormat><ProfileCharacterFormat/></DataFormat></FlatFileElement><FlatFileElement dataType="character" enforceUnique="false" isMappable="true" isNode="true" key="65" mandatory="false" maxLength="0" minLength="0" name="2421" useToIdentifyFormat="false" validateData="false"><DataFormat><ProfileCharacterFormat/></DataFormat></FlatFileElement><FlatFileElement dataType="character" enforceUnique="false" isMappable="true" isNode="true" key="66" mandatory="false" maxLength="0" minLength="0" name="2426" useToIdentifyFormat="false" validateData="false"><DataFormat><ProfileCharacterFormat/></DataFormat></FlatFileElement><FlatFileElement dataType="character" enforceUnique="false" isMappable="true" isNode="true" key="67" mandatory="false" maxLength="0" minLength="0" name="2427" useToIdentifyFormat="false" validateData="false"><DataFormat><ProfileCharacterFormat/></DataFormat></FlatFileElement><FlatFileElement dataType="character" enforceUnique="false" isMappable="true" isNode="true" key="68" mandatory="false" maxLength="0" minLength="0" name="2428" useToIdentifyFormat="false" validateData="false"><DataFormat><ProfileCharacterFormat/></DataFormat></FlatFileElement><FlatFileElement dataType="character" enforceUnique="false" isMappable="true" isNode="true" key="69" mandatory="false" maxLength="0" minLength="0" name="2429" useToIdentifyFormat="false" validateData="false"><DataFormat><ProfileCharacterFormat/></DataFormat></FlatFileElement><FlatFileElement dataType="character" enforceUnique="false" isMappable="true" isNode="true" key="70" mandatory="false" maxLength="0" minLength="0" name="2436" useToIdentifyFormat="false" validateData="false"><DataFormat><ProfileCharacterFormat/></DataFormat></FlatFileElement><FlatFileElement dataType="character" enforceUnique="false" isMappable="true" isNode="true" key="71" mandatory="false" maxLength="0" minLength="0" name="2437" useToIdentifyFormat="false" validateData="false"><DataFormat><ProfileCharacterFormat/></DataFormat></FlatFileElement><FlatFileElement dataType="character" enforceUnique="false" isMappable="true" isNode="true" key="72" mandatory="false" maxLength="0" minLength="0" name="2441" useToIdentifyFormat="false" validateData="false"><DataFormat><ProfileCharacterFormat/></DataFormat></FlatFileElement><FlatFileElement dataType="character" enforceUnique="false" isMappable="true" isNode="true" key="73" mandatory="false" maxLength="0" minLength="0" name="2442" useToIdentifyFormat="false" validateData="false"><DataFormat><ProfileCharacterFormat/></DataFormat></FlatFileElement><FlatFileElement dataType="character" enforceUnique="false" isMappable="true" isNode="true" key="74" mandatory="false" maxLength="0" minLength="0" name="2443" useToIdentifyFormat="false" validateData="false"><DataFormat><ProfileCharacterFormat/></DataFormat></FlatFileElement><FlatFileElement dataType="character" enforceUnique="false" isMappable="true" isNode="true" key="75" mandatory="false" maxLength="0" minLength="0" name="2444" useToIdentifyFormat="false" validateData="false"><DataFormat><ProfileCharacterFormat/></DataFormat></FlatFileElement><FlatFileElement dataType="character" enforceUnique="false" isMappable="true" isNode="true" key="76" mandatory="false" maxLength="0" minLength="0" name="2446" useToIdentifyFormat="false" validateData="false"><DataFormat><ProfileCharacterFormat/></DataFormat></FlatFileElement><FlatFileElement dataType="character" enforceUnique="false" isMappable="true" isNode="true" key="77" mandatory="false" maxLength="0" minLength="0" name="2447" useToIdentifyFormat="false" validateData="false"><DataFormat><ProfileCharacterFormat/></DataFormat></FlatFileElement><FlatFileElement dataType="character" enforceUnique="false" isMappable="true" isNode="true" key="78" mandatory="false" maxLength="0" minLength="0" name="2448" useToIdentifyFormat="false" validateData="false"><DataFormat><ProfileCharacterFormat/></DataFormat></FlatFileElement><FlatFileElement dataType="character" enforceUnique="false" isMappable="true" isNode="true" key="79" mandatory="false" maxLength="0" minLength="0" name="2449" useToIdentifyFormat="false" validateData="false"><DataFormat><ProfileCharacterFormat/></DataFormat></FlatFileElement><FlatFileElement dataType="character" enforceUnique="false" isMappable="true" isNode="true" key="80" mandatory="false" maxLength="0" minLength="0" name="2601" useToIdentifyFormat="false" validateData="false"><DataFormat><ProfileCharacterFormat/></DataFormat></FlatFileElement><FlatFileElement dataType="character" enforceUnique="false" isMappable="true" isNode="true" key="81" mandatory="false" maxLength="0" minLength="0" name="2602" useToIdentifyFormat="false" validateData="false"><DataFormat><ProfileCharacterFormat/></DataFormat></FlatFileElement><FlatFileElement dataType="character" enforceUnique="false" isMappable="true" isNode="true" key="82" mandatory="false" maxLength="0" minLength="0" name="2603" useToIdentifyFormat="false" validateData="false"><DataFormat><ProfileCharacterFormat/></DataFormat></FlatFileElement><FlatFileElement dataType="character" enforceUnique="false" isMappable="true" isNode="true" key="83" mandatory="false" maxLength="0" minLength="0" name="2604" useToIdentifyFormat="false" validateData="false"><DataFormat><ProfileCharacterFormat/></DataFormat></FlatFileElement><FlatFileElement dataType="character" enforceUnique="false" isMappable="true" isNode="true" key="84" mandatory="false" maxLength="0" minLength="0" name="2605" useToIdentifyFormat="false" validateData="false"><DataFormat><ProfileCharacterFormat/></DataFormat></FlatFileElement><FlatFileElement dataType="character" enforceUnique="false" isMappable="true" isNode="true" key="85" mandatory="false" maxLength="0" minLength="0" name="2606" useToIdentifyFormat="false" validateData="false"><DataFormat><ProfileCharacterFormat/></DataFormat></FlatFileElement><FlatFileElement dataType="character" enforceUnique="false" isMappable="true" isNode="true" key="86" mandatory="false" maxLength="0" minLength="0" name="2607" useToIdentifyFormat="false" validateData="false"><DataFormat><ProfileCharacterFormat/></DataFormat></FlatFileElement><FlatFileElement dataType="character" enforceUnique="false" isMappable="true" isNode="true" key="87" mandatory="false" maxLength="0" minLength="0" name="2608" useToIdentifyFormat="false" validateData="false"><DataFormat><ProfileCharacterFormat/></DataFormat></FlatFileElement><FlatFileElement dataType="character" enforceUnique="false" isMappable="true" isNode="true" key="88" mandatory="false" maxLength="0" minLength="0" name="2609" useToIdentifyFormat="false" validateData="false"><DataFormat><ProfileCharacterFormat/></DataFormat></FlatFileElement><FlatFileElement dataType="character" enforceUnique="false" isMappable="true" isNode="true" key="89" mandatory="false" maxLength="0" minLength="0" name="2610" useToIdentifyFormat="false" validateData="false"><DataFormat><ProfileCharacterFormat/></DataFormat></FlatFileElement><FlatFileElement dataType="character" enforceUnique="false" isMappable="true" isNode="true" key="90" mandatory="false" maxLength="0" minLength="0" name="2611" useToIdentifyFormat="false" validateData="false"><DataFormat><ProfileCharacterFormat/></DataFormat></FlatFileElement><FlatFileElement dataType="character" enforceUnique="false" isMappable="true" isNode="true" key="91" mandatory="false" maxLength="0" minLength="0" name="2612" useToIdentifyFormat="false" validateData="false"><DataFormat><ProfileCharacterFormat/></DataFormat></FlatFileElement><FlatFileElement dataType="character" enforceUnique="false" isMappable="true" isNode="true" key="92" mandatory="false" maxLength="0" minLength="0" name="2613" useToIdentifyFormat="false" validateData="false"><DataFormat><ProfileCharacterFormat/></DataFormat></FlatFileElement><FlatFileElement dataType="character" enforceUnique="false" isMappable="true" isNode="true" key="93" mandatory="false" maxLength="0" minLength="0" name="2614" useToIdentifyFormat="false" validateData="false"><DataFormat><ProfileCharacterFormat/></DataFormat></FlatFileElement><FlatFileElement dataType="character" enforceUnique="false" isMappable="true" isNode="true" key="94" mandatory="false" maxLength="0" minLength="0" name="2615" useToIdentifyFormat="false" validateData="false"><DataFormat><ProfileCharacterFormat/></DataFormat></FlatFileElement><FlatFileElement dataType="character" enforceUnique="false" isMappable="true" isNode="true" key="95" mandatory="false" maxLength="0" minLength="0" name="2616" useToIdentifyFormat="false" validateData="false"><DataFormat><ProfileCharacterFormat/></DataFormat></FlatFileElement><FlatFileElement dataType="character" enforceUnique="false" isMappable="true" isNode="true" key="96" mandatory="false" maxLength="0" minLength="0" name="2617" useToIdentifyFormat="false" validateData="false"><DataFormat><ProfileCharacterFormat/></DataFormat></FlatFileElement><FlatFileElement dataType="character" enforceUnique="false" isMappable="true" isNode="true" key="97" mandatory="false" maxLength="0" minLength="0" name="2618" useToIdentifyFormat="false" validateData="false"><DataFormat><ProfileCharacterFormat/></DataFormat></FlatFileElement><FlatFileElement dataType="character" enforceUnique="false" isMappable="true" isNode="true" key="98" mandatory="false" maxLength="0" minLength="0" name="2619" useToIdentifyFormat="false" validateData="false"><DataFormat><ProfileCharacterFormat/></DataFormat></FlatFileElement><FlatFileElement dataType="character" enforceUnique="false" isMappable="true" isNode="true" key="99" mandatory="false" maxLength="0" minLength="0" name="2620" useToIdentifyFormat="false" validateData="false"><DataFormat><ProfileCharacterFormat/></DataFormat></FlatFileElement><FlatFileElement dataType="character" enforceUnique="false" isMappable="true" isNode="true" key="100" mandatory="false" maxLength="0" minLength="0" name="2621" useToIdentifyFormat="false" validateData="false"><DataFormat><ProfileCharacterFormat/></DataFormat></FlatFileElement><FlatFileElement dataType="character" enforceUnique="false" isMappable="true" isNode="true" key="101" mandatory="false" maxLength="0" minLength="0" name="2622" useToIdentifyFormat="false" validateData="false"><DataFormat><ProfileCharacterFormat/></DataFormat></FlatFileElement><FlatFileElement dataType="character" enforceUnique="false" isMappable="true" isNode="true" key="102" mandatory="false" maxLength="0" minLength="0" name="2623" useToIdentifyFormat="false" validateData="false"><DataFormat><ProfileCharacterFormat/></DataFormat></FlatFileElement><FlatFileElement dataType="character" enforceUnique="false" isMappable="true" isNode="true" key="103" mandatory="false" maxLength="0" minLength="0" name="2624" useToIdentifyFormat="false" validateData="false"><DataFormat><ProfileCharacterFormat/></DataFormat></FlatFileElement><FlatFileElement dataType="character" enforceUnique="false" isMappable="true" isNode="true" key="104" mandatory="false" maxLength="0" minLength="0" name="2625" useToIdentifyFormat="false" validateData="false"><DataFormat><ProfileCharacterFormat/></DataFormat></FlatFileElement><FlatFileElement dataType="character" enforceUnique="false" isMappable="true" isNode="true" key="105" mandatory="false" maxLength="0" minLength="0" name="2626" useToIdentifyFormat="false" validateData="false"><DataFormat><ProfileCharacterFormat/></DataFormat></FlatFileElement><FlatFileElement dataType="character" enforceUnique="false" isMappable="true" isNode="true" key="106" mandatory="false" maxLength="0" minLength="0" name="2627" useToIdentifyFormat="false" validateData="false"><DataFormat><ProfileCharacterFormat/></DataFormat></FlatFileElement><FlatFileElement dataType="character" enforceUnique="false" isMappable="true" isNode="true" key="107" mandatory="false" maxLength="0" minLength="0" name="2628" useToIdentifyFormat="false" validateData="false"><DataFormat><ProfileCharacterFormat/></DataFormat></FlatFileElement><FlatFileElement dataType="character" enforceUnique="false" isMappable="true" isNode="true" key="108" mandatory="false" maxLength="0" minLength="0" name="2629" useToIdentifyFormat="false" validateData="false"><DataFormat><ProfileCharacterFormat/></DataFormat></FlatFileElement><FlatFileElement dataType="character" enforceUnique="false" isMappable="true" isNode="true" key="109" mandatory="false" maxLength="0" minLength="0" name="2630" useToIdentifyFormat="false" validateData="false"><DataFormat><ProfileCharacterFormat/></DataFormat></FlatFileElement><FlatFileElement dataType="character" enforceUnique="false" isMappable="true" isNode="true" key="110" mandatory="false" maxLength="0" minLength="0" name="2631" useToIdentifyFormat="false" validateData="false"><DataFormat><ProfileCharacterFormat/></DataFormat></FlatFileElement><FlatFileElement dataType="character" enforceUnique="false" isMappable="true" isNode="true" key="111" mandatory="false" maxLength="0" minLength="0" name="2632" useToIdentifyFormat="false" validateData="false"><DataFormat><ProfileCharacterFormat/></DataFormat></FlatFileElement><FlatFileElement dataType="character" enforceUnique="false" isMappable="true" isNode="true" key="112" mandatory="false" maxLength="0" minLength="0" name="2633" useToIdentifyFormat="false" validateData="false"><DataFormat><ProfileCharacterFormat/></DataFormat></FlatFileElement><FlatFileElement dataType="character" enforceUnique="false" isMappable="true" isNode="true" key="113" mandatory="false" maxLength="0" minLength="0" name="2634" useToIdentifyFormat="false" validateData="false"><DataFormat><ProfileCharacterFormat/></DataFormat></FlatFileElement><FlatFileElement dataType="character" enforceUnique="false" isMappable="true" isNode="true" key="114" mandatory="false" maxLength="0" minLength="0" name="2635" useToIdentifyFormat="false" validateData="false"><DataFormat><ProfileCharacterFormat/></DataFormat></FlatFileElement><FlatFileElement dataType="character" enforceUnique="false" isMappable="true" isNode="true" key="115" mandatory="false" maxLength="0" minLength="0" name="2636" useToIdentifyFormat="false" validateData="false"><DataFormat><ProfileCharacterFormat/></DataFormat></FlatFileElement><FlatFileElement dataType="character" enforceUnique="false" isMappable="true" isNode="true" key="116" mandatory="false" maxLength="0" minLength="0" name="2637" useToIdentifyFormat="false" validateData="false"><DataFormat><ProfileCharacterFormat/></DataFormat></FlatFileElement><FlatFileElement dataType="character" enforceUnique="false" isMappable="true" isNode="true" key="117" mandatory="false" maxLength="0" minLength="0" name="2638" useToIdentifyFormat="false" validateData="false"><DataFormat><ProfileCharacterFormat/></DataFormat></FlatFileElement><FlatFileElement dataType="character" enforceUnique="false" isMappable="true" isNode="true" key="118" mandatory="false" maxLength="0" minLength="0" name="2639" useToIdentifyFormat="false" validateData="false"><DataFormat><ProfileCharacterFormat/></DataFormat></FlatFileElement><FlatFileElement dataType="character" enforceUnique="false" isMappable="true" isNode="true" key="119" mandatory="false" maxLength="0" minLength="0" name="2640" useToIdentifyFormat="false" validateData="false"><DataFormat><ProfileCharacterFormat/></DataFormat></FlatFileElement><FlatFileElement dataType="character" enforceUnique="false" isMappable="true" isNode="true" key="120" mandatory="false" maxLength="0" minLength="0" name="2641" useToIdentifyFormat="false" validateData="false"><DataFormat><ProfileCharacterFormat/></DataFormat></FlatFileElement><FlatFileElement dataType="character" enforceUnique="false" isMappable="true" isNode="true" key="121" mandatory="false" maxLength="0" minLength="0" name="2642" useToIdentifyFormat="false" validateData="false"><DataFormat><ProfileCharacterFormat/></DataFormat></FlatFileElement><FlatFileElement dataType="character" enforceUnique="false" isMappable="true" isNode="true" key="122" mandatory="false" maxLength="0" minLength="0" name="2643" useToIdentifyFormat="false" validateData="false"><DataFormat><ProfileCharacterFormat/></DataFormat></FlatFileElement><FlatFileElement dataType="character" enforceUnique="false" isMappable="true" isNode="true" key="123" mandatory="false" maxLength="0" minLength="0" name="2644" useToIdentifyFormat="false" validateData="false"><DataFormat><ProfileCharacterFormat/></DataFormat></FlatFileElement><FlatFileElement dataType="character" enforceUnique="false" isMappable="true" isNode="true" key="124" mandatory="false" maxLength="0" minLength="0" name="2645" useToIdentifyFormat="false" validateData="false"><DataFormat><ProfileCharacterFormat/></DataFormat></FlatFileElement><FlatFileElement dataType="character" enforceUnique="false" isMappable="true" isNode="true" key="125" mandatory="false" maxLength="0" minLength="0" name="2556" useToIdentifyFormat="false" validateData="false"><DataFormat><ProfileCharacterFormat/></DataFormat></FlatFileElement><FlatFileElement dataType="character" enforceUnique="false" isMappable="true" isNode="true" key="126" mandatory="false" maxLength="0" minLength="0" name="2557" useToIdentifyFormat="false" validateData="false"><DataFormat><ProfileCharacterFormat/></DataFormat></FlatFileElement><FlatFileElement dataType="character" enforceUnique="false" isMappable="true" isNode="true" key="127" mandatory="false" maxLength="0" minLength="0" name="2558" useToIdentifyFormat="false" validateData="false"><DataFormat><ProfileCharacterFormat/></DataFormat></FlatFileElement></FlatFileElements></FlatFileRecord></DataElements></FlatFileProfile></bns:object></bns:Component>