<?xml version="1.0" encoding="UTF-8" standalone="yes"?><bns:Component xmlns:xsi="http://www.w3.org/2001/XMLSchema-instance" xmlns:bns="http://api.platform.boomi.com/" folderFullPath="JERA Co., Inc./TEST" componentId="cae2a1d2-a9c4-40d4-acf9-74b1ccc2e7c8" version="1" name="BAPI_FUNCLOC_GETLIST_response" type="profile.xml" createdDate="2021-04-07T03:23:45Z" createdBy="Daly.Fadhloun@avaxia-group.com" modifiedDate="2021-04-07T03:23:45Z" modifiedBy="Daly.Fadhloun@avaxia-group.com" deleted="false" currentVersion="true" folderName="TEST" folderId="RjoyOTk4NzM0" branchName="main" branchId="QjozMzg0ODI"><bns:encryptedValues/><bns:object><XMLProfile xmlns="" modelVersion="2" strict="true"><ProfileProperties><XMLGeneralInfo/><XMLOptions encoding="utf8" implicitElementOrdering="true" parseRespectMaxOccurs="true"/></ProfileProperties><DataElements><XMLElement dataType="character" isMappable="true" isNode="true" key="1" maxOccurs="1" minOccurs="1" name="BAPI_FUNCLOC_GETLIST" typeExpanded="false" typeKey="-1" useNamespace="-1"><DataFormat><ProfileCharacterFormat/></DataFormat><XMLElement comments="BAPI Communication Structure: Range for Address City" dataType="character" isMappable="true" isNode="true" key="189" loopingOption="unique" maxOccurs="1" minOccurs="0" name="ADDRESS_CITY_RA" typeExpanded="false" typeKey="-1" useNamespace="-1" validateData="false"><DataFormat><ProfileCharacterFormat/></DataFormat><XMLElement dataType="character" isMappable="true" isNode="true" key="223" loopingOption="unique" maxOccurs="-1" minOccurs="0" name="item" typeExpanded="true" typeKey="8" typeName="BAPI_ITOB_SEL_ADDR_CITY" useNamespace="-1" validateData="false"><DataFormat><ProfileCharacterFormat/></DataFormat><XMLElement comments="範囲データ型の行データ型: タイプ SIGN のコンポーネント" dataType="character" isMappable="true" isNode="true" key="283" loopingOption="unique" maxLength="1" maxOccurs="1" minLength="0" minOccurs="0" name="SIGN" typeKey="-1" useNamespace="-1" validateData="true"><DataFormat><ProfileCharacterFormat/></DataFormat></XMLElement><XMLElement comments="範囲データ型の行データ型のタイプ OPTION のコンポーネント" dataType="character" isMappable="true" isNode="true" key="285" loopingOption="unique" maxLength="2" maxOccurs="1" minLength="0" minOccurs="0" name="OPTION" typeKey="-1" useNamespace="-1" validateData="true"><DataFormat><ProfileCharacterFormat/></DataFormat></XMLElement><XMLElement comments="検索ヘルプ用大文字の市区町村名" dataType="character" isMappable="true" isNode="true" key="287" loopingOption="unique" maxLength="25" maxOccurs="1" minLength="0" minOccurs="0" name="LOW" typeKey="-1" useNamespace="-1" validateData="true"><DataFormat><ProfileCharacterFormat/></DataFormat></XMLElement><XMLElement comments="検索ヘルプ用大文字の市区町村名" dataType="character" isMappable="true" isNode="true" key="289" loopingOption="unique" maxLength="25" maxOccurs="1" minLength="0" minOccurs="0" name="HIGH" typeKey="-1" useNamespace="-1" validateData="true"><DataFormat><ProfileCharacterFormat/></DataFormat></XMLElement></XMLElement></XMLElement><XMLElement comments="BAPI Communication Structure: Range for Address Name" dataType="character" isMappable="true" isNode="true" key="191" loopingOption="unique" maxOccurs="1" minOccurs="0" name="ADDRESS_NAME_RA" typeExpanded="false" typeKey="-1" useNamespace="-1" validateData="false"><DataFormat><ProfileCharacterFormat/></DataFormat><XMLElement dataType="character" isMappable="true" isNode="true" key="225" loopingOption="unique" maxOccurs="-1" minOccurs="0" name="item" typeExpanded="true" typeKey="18" typeName="BAPI_ITOB_SEL_ADDR_NAME" useNamespace="-1" validateData="false"><DataFormat><ProfileCharacterFormat/></DataFormat><XMLElement comments="範囲データ型の行データ型: タイプ SIGN のコンポーネント" dataType="character" isMappable="true" isNode="true" key="291" loopingOption="unique" maxLength="1" maxOccurs="1" minLength="0" minOccurs="0" name="SIGN" typeKey="-1" useNamespace="-1" validateData="true"><DataFormat><ProfileCharacterFormat/></DataFormat></XMLElement><XMLElement comments="範囲データ型の行データ型のタイプ OPTION のコンポーネント" dataType="character" isMappable="true" isNode="true" key="293" loopingOption="unique" maxLength="2" maxOccurs="1" minLength="0" minOccurs="0" name="OPTION" typeKey="-1" useNamespace="-1" validateData="true"><DataFormat><ProfileCharacterFormat/></DataFormat></XMLElement><XMLElement comments="マッチコード用大文字の名称 (項目 NAME1)" dataType="character" isMappable="true" isNode="true" key="295" loopingOption="unique" maxLength="25" maxOccurs="1" minLength="0" minOccurs="0" name="LOW" typeKey="-1" useNamespace="-1" validateData="true"><DataFormat><ProfileCharacterFormat/></DataFormat></XMLElement><XMLElement comments="マッチコード用大文字の名称 (項目 NAME1)" dataType="character" isMappable="true" isNode="true" key="297" loopingOption="unique" maxLength="25" maxOccurs="1" minLength="0" minOccurs="0" name="HIGH" typeKey="-1" useNamespace="-1" validateData="true"><DataFormat><ProfileCharacterFormat/></DataFormat></XMLElement></XMLElement></XMLElement><XMLElement comments="BAPI Communication Structure: Range for Address Postal Code" dataType="character" isMappable="true" isNode="true" key="193" loopingOption="unique" maxOccurs="1" minOccurs="0" name="ADDRESS_POST_CODE_RA" typeExpanded="false" typeKey="-1" useNamespace="-1" validateData="false"><DataFormat><ProfileCharacterFormat/></DataFormat><XMLElement dataType="character" isMappable="true" isNode="true" key="227" loopingOption="unique" maxOccurs="-1" minOccurs="0" name="item" typeExpanded="true" typeKey="28" typeName="BAPI_ITOB_SEL_ADDR_POST_CODE" useNamespace="-1" validateData="false"><DataFormat><ProfileCharacterFormat/></DataFormat><XMLElement comments="範囲データ型の行データ型: タイプ SIGN のコンポーネント" dataType="character" isMappable="true" isNode="true" key="299" loopingOption="unique" maxLength="1" maxOccurs="1" minLength="0" minOccurs="0" name="SIGN" typeKey="-1" useNamespace="-1" validateData="true"><DataFormat><ProfileCharacterFormat/></DataFormat></XMLElement><XMLElement comments="範囲データ型の行データ型のタイプ OPTION のコンポーネント" dataType="character" isMappable="true" isNode="true" key="301" loopingOption="unique" maxLength="2" maxOccurs="1" minLength="0" minOccurs="0" name="OPTION" typeKey="-1" useNamespace="-1" validateData="true"><DataFormat><ProfileCharacterFormat/></DataFormat></XMLElement><XMLElement comments="市区町村の郵便番号" dataType="character" isMappable="true" isNode="true" key="303" loopingOption="unique" maxLength="10" maxOccurs="1" minLength="0" minOccurs="0" name="LOW" typeKey="-1" useNamespace="-1" validateData="true"><DataFormat><ProfileCharacterFormat/></DataFormat></XMLElement><XMLElement comments="市区町村の郵便番号" dataType="character" isMappable="true" isNode="true" key="305" loopingOption="unique" maxLength="10" maxOccurs="1" minLength="0" minOccurs="0" name="HIGH" typeKey="-1" useNamespace="-1" validateData="true"><DataFormat><ProfileCharacterFormat/></DataFormat></XMLElement></XMLElement></XMLElement><XMLElement comments="BAPI Communication Structure: Range for Address Search Term 1" dataType="character" isMappable="true" isNode="true" key="195" loopingOption="unique" maxOccurs="1" minOccurs="0" name="ADDRESS_SEARCH_TERM_1_RA" typeExpanded="false" typeKey="-1" useNamespace="-1" validateData="false"><DataFormat><ProfileCharacterFormat/></DataFormat><XMLElement dataType="character" isMappable="true" isNode="true" key="229" loopingOption="unique" maxOccurs="-1" minOccurs="0" name="item" typeExpanded="true" typeKey="38" typeName="BAPI_ITOB_SEL_ADDR_SORT1" useNamespace="-1" validateData="false"><DataFormat><ProfileCharacterFormat/></DataFormat><XMLElement comments="範囲データ型の行データ型: タイプ SIGN のコンポーネント" dataType="character" isMappable="true" isNode="true" key="307" loopingOption="unique" maxLength="1" maxOccurs="1" minLength="0" minOccurs="0" name="SIGN" typeKey="-1" useNamespace="-1" validateData="true"><DataFormat><ProfileCharacterFormat/></DataFormat></XMLElement><XMLElement comments="範囲データ型の行データ型のタイプ OPTION のコンポーネント" dataType="character" isMappable="true" isNode="true" key="309" loopingOption="unique" maxLength="2" maxOccurs="1" minLength="0" minOccurs="0" name="OPTION" typeKey="-1" useNamespace="-1" validateData="true"><DataFormat><ProfileCharacterFormat/></DataFormat></XMLElement><XMLElement comments="検索語句 1" dataType="character" isMappable="true" isNode="true" key="311" loopingOption="unique" maxLength="20" maxOccurs="1" minLength="0" minOccurs="0" name="LOW" typeKey="-1" useNamespace="-1" validateData="true"><DataFormat><ProfileCharacterFormat/></DataFormat></XMLElement><XMLElement comments="検索語句 1" dataType="character" isMappable="true" isNode="true" key="313" loopingOption="unique" maxLength="20" maxOccurs="1" minLength="0" minOccurs="0" name="HIGH" typeKey="-1" useNamespace="-1" validateData="true"><DataFormat><ProfileCharacterFormat/></DataFormat></XMLElement></XMLElement></XMLElement><XMLElement comments="BAPI Communication Structure: Range for Address Search Term 2" dataType="character" isMappable="true" isNode="true" key="197" loopingOption="unique" maxOccurs="1" minOccurs="0" name="ADDRESS_SEARCH_TERM_2_RA" typeExpanded="false" typeKey="-1" useNamespace="-1" validateData="false"><DataFormat><ProfileCharacterFormat/></DataFormat><XMLElement dataType="character" isMappable="true" isNode="true" key="231" loopingOption="unique" maxOccurs="-1" minOccurs="0" name="item" typeExpanded="true" typeKey="48" typeName="BAPI_ITOB_SEL_ADDR_SORT2" useNamespace="-1" validateData="false"><DataFormat><ProfileCharacterFormat/></DataFormat><XMLElement comments="範囲データ型の行データ型: タイプ SIGN のコンポーネント" dataType="character" isMappable="true" isNode="true" key="315" loopingOption="unique" maxLength="1" maxOccurs="1" minLength="0" minOccurs="0" name="SIGN" typeKey="-1" useNamespace="-1" validateData="true"><DataFormat><ProfileCharacterFormat/></DataFormat></XMLElement><XMLElement comments="範囲データ型の行データ型のタイプ OPTION のコンポーネント" dataType="character" isMappable="true" isNode="true" key="317" loopingOption="unique" maxLength="2" maxOccurs="1" minLength="0" minOccurs="0" name="OPTION" typeKey="-1" useNamespace="-1" validateData="true"><DataFormat><ProfileCharacterFormat/></DataFormat></XMLElement><XMLElement comments="検索語句 2" dataType="character" isMappable="true" isNode="true" key="319" loopingOption="unique" maxLength="20" maxOccurs="1" minLength="0" minOccurs="0" name="LOW" typeKey="-1" useNamespace="-1" validateData="true"><DataFormat><ProfileCharacterFormat/></DataFormat></XMLElement><XMLElement comments="検索語句 2" dataType="character" isMappable="true" isNode="true" key="321" loopingOption="unique" maxLength="20" maxOccurs="1" minLength="0" minOccurs="0" name="HIGH" typeKey="-1" useNamespace="-1" validateData="true"><DataFormat><ProfileCharacterFormat/></DataFormat></XMLElement></XMLElement></XMLElement><XMLElement comments="BAPI Communication Structure: Range for Address Street" dataType="character" isMappable="true" isNode="true" key="199" loopingOption="unique" maxOccurs="1" minOccurs="0" name="ADDRESS_STREET_RA" typeExpanded="false" typeKey="-1" useNamespace="-1" validateData="false"><DataFormat><ProfileCharacterFormat/></DataFormat><XMLElement dataType="character" isMappable="true" isNode="true" key="233" loopingOption="unique" maxOccurs="-1" minOccurs="0" name="item" typeExpanded="true" typeKey="58" typeName="BAPI_ITOB_SEL_ADDR_STREET" useNamespace="-1" validateData="false"><DataFormat><ProfileCharacterFormat/></DataFormat><XMLElement comments="範囲データ型の行データ型: タイプ SIGN のコンポーネント" dataType="character" isMappable="true" isNode="true" key="323" loopingOption="unique" maxLength="1" maxOccurs="1" minLength="0" minOccurs="0" name="SIGN" typeKey="-1" useNamespace="-1" validateData="true"><DataFormat><ProfileCharacterFormat/></DataFormat></XMLElement><XMLElement comments="範囲データ型の行データ型のタイプ OPTION のコンポーネント" dataType="character" isMappable="true" isNode="true" key="325" loopingOption="unique" maxLength="2" maxOccurs="1" minLength="0" minOccurs="0" name="OPTION" typeKey="-1" useNamespace="-1" validateData="true"><DataFormat><ProfileCharacterFormat/></DataFormat></XMLElement><XMLElement comments="検索ヘルプ用大文字の地名" dataType="character" isMappable="true" isNode="true" key="327" loopingOption="unique" maxLength="25" maxOccurs="1" minLength="0" minOccurs="0" name="LOW" typeKey="-1" useNamespace="-1" validateData="true"><DataFormat><ProfileCharacterFormat/></DataFormat></XMLElement><XMLElement comments="検索ヘルプ用大文字の地名" dataType="character" isMappable="true" isNode="true" key="329" loopingOption="unique" maxLength="25" maxOccurs="1" minLength="0" minOccurs="0" name="HIGH" typeKey="-1" useNamespace="-1" validateData="true"><DataFormat><ProfileCharacterFormat/></DataFormat></XMLElement></XMLElement></XMLElement><XMLElement comments="BAPI 通信構造: テキストの範囲" dataType="character" isMappable="true" isNode="true" key="201" loopingOption="unique" maxOccurs="1" minOccurs="0" name="DESCRIPT_RA" typeExpanded="false" typeKey="-1" useNamespace="-1" validateData="false"><DataFormat><ProfileCharacterFormat/></DataFormat><XMLElement dataType="character" isMappable="true" isNode="true" key="235" loopingOption="unique" maxOccurs="-1" minOccurs="0" name="item" typeExpanded="true" typeKey="68" typeName="BAPI_ITOB_SEL_DESCRIPT" useNamespace="-1" validateData="false"><DataFormat><ProfileCharacterFormat/></DataFormat><XMLElement comments="選択演算子 SIGN (テーブル範囲)" dataType="character" isMappable="true" isNode="true" key="331" loopingOption="unique" maxLength="1" maxOccurs="1" minLength="0" minOccurs="0" name="SIGN" typeKey="-1" useNamespace="-1" validateData="true"><DataFormat><ProfileCharacterFormat/></DataFormat></XMLElement><XMLElement comments="選択演算子 OPTION (範囲テーブル)" dataType="character" isMappable="true" isNode="true" key="333" loopingOption="unique" maxLength="2" maxOccurs="1" minLength="0" minOccurs="0" name="OPTION" typeKey="-1" useNamespace="-1" validateData="true"><DataFormat><ProfileCharacterFormat/></DataFormat></XMLElement><XMLElement comments="技術対象テキスト" dataType="character" isMappable="true" isNode="true" key="335" loopingOption="unique" maxLength="40" maxOccurs="1" minLength="0" minOccurs="0" name="LOW" typeKey="-1" useNamespace="-1" validateData="true"><DataFormat><ProfileCharacterFormat/></DataFormat></XMLElement><XMLElement comments="技術対象テキスト" dataType="character" isMappable="true" isNode="true" key="337" loopingOption="unique" maxLength="40" maxOccurs="1" minLength="0" minOccurs="0" name="HIGH" typeKey="-1" useNamespace="-1" validateData="true"><DataFormat><ProfileCharacterFormat/></DataFormat></XMLElement></XMLElement></XMLElement><XMLElement comments="BAPI 通信構造: 選択結果一覧" dataType="character" isMappable="true" isNode="true" key="203" loopingOption="unique" maxOccurs="1" minOccurs="1" name="FUNCLOC_LIST" typeExpanded="false" typeKey="-1" useNamespace="-1" validateData="false"><DataFormat><ProfileCharacterFormat/></DataFormat><XMLElement dataType="character" isMappable="true" isNode="true" key="237" loopingOption="unique" maxOccurs="-1" minOccurs="0" name="item" typeExpanded="true" typeKey="78" typeName="BAPI_ITOB_FL_SEL_RESULT" useNamespace="-1" validateData="false"><DataFormat><ProfileCharacterFormat/></DataFormat><XMLElement comments="機能場所" dataType="character" isMappable="true" isNode="true" key="339" loopingOption="unique" maxLength="30" maxOccurs="1" minLength="0" minOccurs="0" name="FUNCTLOCATION" typeKey="-1" useNamespace="-1" validateData="true"><DataFormat><ProfileCharacterFormat/></DataFormat></XMLElement><XMLElement comments="機能場所ラベル" dataType="character" isMappable="true" isNode="true" key="341" loopingOption="unique" maxLength="40" maxOccurs="1" minLength="0" minOccurs="0" name="FUNCLOC" typeKey="-1" useNamespace="-1" validateData="true"><DataFormat><ProfileCharacterFormat/></DataFormat></XMLElement><XMLElement comments="機能場所のラベルシステム" dataType="character" isMappable="true" isNode="true" key="343" loopingOption="unique" maxLength="1" maxOccurs="1" minLength="0" minOccurs="0" name="LABEL_SYST" typeKey="-1" useNamespace="-1" validateData="true"><DataFormat><ProfileCharacterFormat/></DataFormat></XMLElement><XMLElement comments="技術対象テキスト" dataType="character" isMappable="true" isNode="true" key="345" loopingOption="unique" maxLength="40" maxOccurs="1" minLength="0" minOccurs="0" name="DESCRIPT" typeKey="-1" useNamespace="-1" validateData="true"><DataFormat><ProfileCharacterFormat/></DataFormat></XMLElement><XMLElement comments="機能場所構成区分" dataType="character" isMappable="true" isNode="true" key="347" loopingOption="unique" maxLength="5" maxOccurs="1" minLength="0" minOccurs="0" name="STRIND" typeKey="-1" useNamespace="-1" validateData="true"><DataFormat><ProfileCharacterFormat/></DataFormat></XMLElement><XMLElement comments="機能場所カテゴリ" dataType="character" isMappable="true" isNode="true" key="349" loopingOption="unique" maxLength="1" maxOccurs="1" minLength="0" minOccurs="0" name="CATEGORY" typeKey="-1" useNamespace="-1" validateData="true"><DataFormat><ProfileCharacterFormat/></DataFormat></XMLElement><XMLElement comments="上位機能場所" dataType="character" isMappable="true" isNode="true" key="351" loopingOption="unique" maxLength="30" maxOccurs="1" minLength="0" minOccurs="0" name="SUPFLOC" typeKey="-1" useNamespace="-1" validateData="true"><DataFormat><ProfileCharacterFormat/></DataFormat></XMLElement><XMLElement comments="保全計画プラント" dataType="character" isMappable="true" isNode="true" key="353" loopingOption="unique" maxLength="4" maxOccurs="1" minLength="0" minOccurs="0" name="PLANPLANT" typeKey="-1" useNamespace="-1" validateData="true"><DataFormat><ProfileCharacterFormat/></DataFormat></XMLElement><XMLElement comments="保全プラント" dataType="character" isMappable="true" isNode="true" key="355" loopingOption="unique" maxLength="4" maxOccurs="1" minLength="0" minOccurs="0" name="MAINTPLANT" typeKey="-1" useNamespace="-1" validateData="true"><DataFormat><ProfileCharacterFormat/></DataFormat></XMLElement><XMLElement comments="得意先サービスおよびプラント保全の計画グループ" dataType="character" isMappable="true" isNode="true" key="357" loopingOption="unique" maxLength="3" maxOccurs="1" minLength="0" minOccurs="0" name="PLANGROUP" typeKey="-1" useNamespace="-1" validateData="true"><DataFormat><ProfileCharacterFormat/></DataFormat></XMLElement><XMLElement comments="ソート項目" dataType="character" isMappable="true" isNode="true" key="359" loopingOption="unique" maxLength="30" maxOccurs="1" minLength="0" minOccurs="0" name="SORTFIELD" typeKey="-1" useNamespace="-1" validateData="true"><DataFormat><ProfileCharacterFormat/></DataFormat></XMLElement></XMLElement></XMLElement><XMLElement comments="BAPI 通信構造: 機能場所の範囲" dataType="character" isMappable="true" isNode="true" key="205" loopingOption="unique" maxOccurs="1" minOccurs="0" name="FUNCLOC_RA" typeExpanded="false" typeKey="-1" useNamespace="-1" validateData="false"><DataFormat><ProfileCharacterFormat/></DataFormat><XMLElement dataType="character" isMappable="true" isNode="true" key="239" loopingOption="unique" maxOccurs="-1" minOccurs="0" name="item" typeExpanded="true" typeKey="95" typeName="BAPI_ITOB_SEL_FUNCLOC" useNamespace="-1" validateData="false"><DataFormat><ProfileCharacterFormat/></DataFormat><XMLElement comments="選択演算子 SIGN (テーブル範囲)" dataType="character" isMappable="true" isNode="true" key="361" loopingOption="unique" maxLength="1" maxOccurs="1" minLength="0" minOccurs="0" name="SIGN" typeKey="-1" useNamespace="-1" validateData="true"><DataFormat><ProfileCharacterFormat/></DataFormat></XMLElement><XMLElement comments="選択演算子 OPTION (範囲テーブル)" dataType="character" isMappable="true" isNode="true" key="363" loopingOption="unique" maxLength="2" maxOccurs="1" minLength="0" minOccurs="0" name="OPTION" typeKey="-1" useNamespace="-1" validateData="true"><DataFormat><ProfileCharacterFormat/></DataFormat></XMLElement><XMLElement comments="機能場所ラベル" dataType="character" isMappable="true" isNode="true" key="365" loopingOption="unique" maxLength="40" maxOccurs="1" minLength="0" minOccurs="0" name="LOW" typeKey="-1" useNamespace="-1" validateData="true"><DataFormat><ProfileCharacterFormat/></DataFormat></XMLElement><XMLElement comments="機能場所ラベル" dataType="character" isMappable="true" isNode="true" key="367" loopingOption="unique" maxLength="40" maxOccurs="1" minLength="0" minOccurs="0" name="HIGH" typeKey="-1" useNamespace="-1" validateData="true"><DataFormat><ProfileCharacterFormat/></DataFormat></XMLElement></XMLElement></XMLElement><XMLElement comments="BAPI 通信構造: 保全プラントの範囲" dataType="character" isMappable="true" isNode="true" key="207" loopingOption="unique" maxOccurs="1" minOccurs="0" name="MAINTPLANT_RA" typeExpanded="false" typeKey="-1" useNamespace="-1" validateData="false"><DataFormat><ProfileCharacterFormat/></DataFormat><XMLElement dataType="character" isMappable="true" isNode="true" key="241" loopingOption="unique" maxOccurs="-1" minOccurs="0" name="item" typeExpanded="true" typeKey="105" typeName="BAPI_ITOB_SEL_MAINTPLANT" useNamespace="-1" validateData="false"><DataFormat><ProfileCharacterFormat/></DataFormat><XMLElement comments="選択演算子 SIGN (テーブル範囲)" dataType="character" isMappable="true" isNode="true" key="369" loopingOption="unique" maxLength="1" maxOccurs="1" minLength="0" minOccurs="0" name="SIGN" typeKey="-1" useNamespace="-1" validateData="true"><DataFormat><ProfileCharacterFormat/></DataFormat></XMLElement><XMLElement comments="選択演算子 OPTION (範囲テーブル)" dataType="character" isMappable="true" isNode="true" key="371" loopingOption="unique" maxLength="2" maxOccurs="1" minLength="0" minOccurs="0" name="OPTION" typeKey="-1" useNamespace="-1" validateData="true"><DataFormat><ProfileCharacterFormat/></DataFormat></XMLElement><XMLElement comments="保全プラント" dataType="character" isMappable="true" isNode="true" key="373" loopingOption="unique" maxLength="4" maxOccurs="1" minLength="0" minOccurs="0" name="LOW" typeKey="-1" useNamespace="-1" validateData="true"><DataFormat><ProfileCharacterFormat/></DataFormat></XMLElement><XMLElement comments="保全プラント" dataType="character" isMappable="true" isNode="true" key="375" loopingOption="unique" maxLength="4" maxOccurs="1" minLength="0" minOccurs="0" name="HIGH" typeKey="-1" useNamespace="-1" validateData="true"><DataFormat><ProfileCharacterFormat/></DataFormat></XMLElement></XMLElement></XMLElement><XMLElement comments="BAPI Communication Structure: Range for Object Type" dataType="character" isMappable="true" isNode="true" key="209" loopingOption="unique" maxOccurs="1" minOccurs="0" name="OBJECTTYPE_RA" typeExpanded="false" typeKey="-1" useNamespace="-1" validateData="false"><DataFormat><ProfileCharacterFormat/></DataFormat><XMLElement dataType="character" isMappable="true" isNode="true" key="243" loopingOption="unique" maxOccurs="-1" minOccurs="0" name="item" typeExpanded="true" typeKey="115" typeName="BAPI_ITOB_SEL_OBJECTTYPE" useNamespace="-1" validateData="false"><DataFormat><ProfileCharacterFormat/></DataFormat><XMLElement comments="範囲データ型の行データ型: タイプ SIGN のコンポーネント" dataType="character" isMappable="true" isNode="true" key="377" loopingOption="unique" maxLength="1" maxOccurs="1" minLength="0" minOccurs="0" name="SIGN" typeKey="-1" useNamespace="-1" validateData="true"><DataFormat><ProfileCharacterFormat/></DataFormat></XMLElement><XMLElement comments="範囲データ型の行データ型のタイプ OPTION のコンポーネント" dataType="character" isMappable="true" isNode="true" key="379" loopingOption="unique" maxLength="2" maxOccurs="1" minLength="0" minOccurs="0" name="OPTION" typeKey="-1" useNamespace="-1" validateData="true"><DataFormat><ProfileCharacterFormat/></DataFormat></XMLElement><XMLElement comments="技術対象タイプ" dataType="character" isMappable="true" isNode="true" key="381" loopingOption="unique" maxLength="10" maxOccurs="1" minLength="0" minOccurs="0" name="LOW" typeKey="-1" useNamespace="-1" validateData="true"><DataFormat><ProfileCharacterFormat/></DataFormat></XMLElement><XMLElement comments="技術対象タイプ" dataType="character" isMappable="true" isNode="true" key="383" loopingOption="unique" maxLength="10" maxOccurs="1" minLength="0" minOccurs="0" name="HIGH" typeKey="-1" useNamespace="-1" validateData="true"><DataFormat><ProfileCharacterFormat/></DataFormat></XMLElement></XMLElement></XMLElement><XMLElement comments="BAPI Communication Structure: Range for Partner" dataType="character" isMappable="true" isNode="true" key="211" loopingOption="unique" maxOccurs="1" minOccurs="0" name="PARTNER_RA" typeExpanded="false" typeKey="-1" useNamespace="-1" validateData="false"><DataFormat><ProfileCharacterFormat/></DataFormat><XMLElement dataType="character" isMappable="true" isNode="true" key="245" loopingOption="unique" maxOccurs="-1" minOccurs="0" name="item" typeExpanded="true" typeKey="125" typeName="BAPI_ITOB_SEL_PARTNER" useNamespace="-1" validateData="false"><DataFormat><ProfileCharacterFormat/></DataFormat><XMLElement comments="範囲データ型の行データ型: タイプ SIGN のコンポーネント" dataType="character" isMappable="true" isNode="true" key="385" loopingOption="unique" maxLength="1" maxOccurs="1" minLength="0" minOccurs="0" name="SIGN" typeKey="-1" useNamespace="-1" validateData="true"><DataFormat><ProfileCharacterFormat/></DataFormat></XMLElement><XMLElement comments="範囲データ型の行データ型のタイプ OPTION のコンポーネント" dataType="character" isMappable="true" isNode="true" key="387" loopingOption="unique" maxLength="2" maxOccurs="1" minLength="0" minOccurs="0" name="OPTION" typeKey="-1" useNamespace="-1" validateData="true"><DataFormat><ProfileCharacterFormat/></DataFormat></XMLElement><XMLElement comments="パートナ" dataType="character" isMappable="true" isNode="true" key="389" loopingOption="unique" maxLength="12" maxOccurs="1" minLength="0" minOccurs="0" name="LOW" typeKey="-1" useNamespace="-1" validateData="true"><DataFormat><ProfileCharacterFormat/></DataFormat></XMLElement><XMLElement comments="パートナ" dataType="character" isMappable="true" isNode="true" key="391" loopingOption="unique" maxLength="12" maxOccurs="1" minLength="0" minOccurs="0" name="HIGH" typeKey="-1" useNamespace="-1" validateData="true"><DataFormat><ProfileCharacterFormat/></DataFormat></XMLElement></XMLElement></XMLElement><XMLElement comments="BAPI 通信構造: 保全計画グループの範囲" dataType="character" isMappable="true" isNode="true" key="213" loopingOption="unique" maxOccurs="1" minOccurs="0" name="PLANGROUP_RA" typeExpanded="false" typeKey="-1" useNamespace="-1" validateData="false"><DataFormat><ProfileCharacterFormat/></DataFormat><XMLElement dataType="character" isMappable="true" isNode="true" key="247" loopingOption="unique" maxOccurs="-1" minOccurs="0" name="item" typeExpanded="true" typeKey="135" typeName="BAPI_ITOB_SEL_PLANGROUP" useNamespace="-1" validateData="false"><DataFormat><ProfileCharacterFormat/></DataFormat><XMLElement comments="選択演算子 SIGN (テーブル範囲)" dataType="character" isMappable="true" isNode="true" key="393" loopingOption="unique" maxLength="1" maxOccurs="1" minLength="0" minOccurs="0" name="SIGN" typeKey="-1" useNamespace="-1" validateData="true"><DataFormat><ProfileCharacterFormat/></DataFormat></XMLElement><XMLElement comments="選択演算子 OPTION (範囲テーブル)" dataType="character" isMappable="true" isNode="true" key="395" loopingOption="unique" maxLength="2" maxOccurs="1" minLength="0" minOccurs="0" name="OPTION" typeKey="-1" useNamespace="-1" validateData="true"><DataFormat><ProfileCharacterFormat/></DataFormat></XMLElement><XMLElement comments="得意先サービスおよびプラント保全の計画グループ" dataType="character" isMappable="true" isNode="true" key="397" loopingOption="unique" maxLength="3" maxOccurs="1" minLength="0" minOccurs="0" name="LOW" typeKey="-1" useNamespace="-1" validateData="true"><DataFormat><ProfileCharacterFormat/></DataFormat></XMLElement><XMLElement comments="得意先サービスおよびプラント保全の計画グループ" dataType="character" isMappable="true" isNode="true" key="399" loopingOption="unique" maxLength="3" maxOccurs="1" minLength="0" minOccurs="0" name="HIGH" typeKey="-1" useNamespace="-1" validateData="true"><DataFormat><ProfileCharacterFormat/></DataFormat></XMLElement></XMLElement></XMLElement><XMLElement comments="BAPI 通信構造: 保全計画の範囲" dataType="character" isMappable="true" isNode="true" key="215" loopingOption="unique" maxOccurs="1" minOccurs="0" name="PLANPLANT_RA" typeExpanded="false" typeKey="-1" useNamespace="-1" validateData="false"><DataFormat><ProfileCharacterFormat/></DataFormat><XMLElement dataType="character" isMappable="true" isNode="true" key="249" loopingOption="unique" maxOccurs="-1" minOccurs="0" name="item" typeExpanded="true" typeKey="145" typeName="BAPI_ITOB_SEL_PLANPLANT" useNamespace="-1" validateData="false"><DataFormat><ProfileCharacterFormat/></DataFormat><XMLElement comments="選択演算子 SIGN (テーブル範囲)" dataType="character" isMappable="true" isNode="true" key="401" loopingOption="unique" maxLength="1" maxOccurs="1" minLength="0" minOccurs="0" name="SIGN" typeKey="-1" useNamespace="-1" validateData="true"><DataFormat><ProfileCharacterFormat/></DataFormat></XMLElement><XMLElement comments="選択演算子 OPTION (範囲テーブル)" dataType="character" isMappable="true" isNode="true" key="403" loopingOption="unique" maxLength="2" maxOccurs="1" minLength="0" minOccurs="0" name="OPTION" typeKey="-1" useNamespace="-1" validateData="true"><DataFormat><ProfileCharacterFormat/></DataFormat></XMLElement><XMLElement comments="保全計画プラント" dataType="character" isMappable="true" isNode="true" key="405" loopingOption="unique" maxLength="4" maxOccurs="1" minLength="0" minOccurs="0" name="LOW" typeKey="-1" useNamespace="-1" validateData="true"><DataFormat><ProfileCharacterFormat/></DataFormat></XMLElement><XMLElement comments="保全計画プラント" dataType="character" isMappable="true" isNode="true" key="407" loopingOption="unique" maxLength="4" maxOccurs="1" minLength="0" minOccurs="0" name="HIGH" typeKey="-1" useNamespace="-1" validateData="true"><DataFormat><ProfileCharacterFormat/></DataFormat></XMLElement></XMLElement></XMLElement><XMLElement comments="BAPI 通信構造: ソート項目の範囲" dataType="character" isMappable="true" isNode="true" key="217" loopingOption="unique" maxOccurs="1" minOccurs="0" name="SORTFIELD_RA" typeExpanded="false" typeKey="-1" useNamespace="-1" validateData="false"><DataFormat><ProfileCharacterFormat/></DataFormat><XMLElement dataType="character" isMappable="true" isNode="true" key="251" loopingOption="unique" maxOccurs="-1" minOccurs="0" name="item" typeExpanded="true" typeKey="155" typeName="BAPI_ITOB_SEL_SORTFIELD" useNamespace="-1" validateData="false"><DataFormat><ProfileCharacterFormat/></DataFormat><XMLElement comments="選択演算子 SIGN (テーブル範囲)" dataType="character" isMappable="true" isNode="true" key="409" loopingOption="unique" maxLength="1" maxOccurs="1" minLength="0" minOccurs="0" name="SIGN" typeKey="-1" useNamespace="-1" validateData="true"><DataFormat><ProfileCharacterFormat/></DataFormat></XMLElement><XMLElement comments="選択演算子 OPTION (範囲テーブル)" dataType="character" isMappable="true" isNode="true" key="411" loopingOption="unique" maxLength="2" maxOccurs="1" minLength="0" minOccurs="0" name="OPTION" typeKey="-1" useNamespace="-1" validateData="true"><DataFormat><ProfileCharacterFormat/></DataFormat></XMLElement><XMLElement comments="ソート項目" dataType="character" isMappable="true" isNode="true" key="413" loopingOption="unique" maxLength="30" maxOccurs="1" minLength="0" minOccurs="0" name="LOW" typeKey="-1" useNamespace="-1" validateData="true"><DataFormat><ProfileCharacterFormat/></DataFormat></XMLElement><XMLElement comments="ソート項目" dataType="character" isMappable="true" isNode="true" key="415" loopingOption="unique" maxLength="30" maxOccurs="1" minLength="0" minOccurs="0" name="HIGH" typeKey="-1" useNamespace="-1" validateData="true"><DataFormat><ProfileCharacterFormat/></DataFormat></XMLElement></XMLElement></XMLElement><XMLElement comments="BAPI Communication Structure: Range for Status" dataType="character" isMappable="true" isNode="true" key="219" loopingOption="unique" maxOccurs="1" minOccurs="0" name="STATUS_RA" typeExpanded="false" typeKey="-1" useNamespace="-1" validateData="false"><DataFormat><ProfileCharacterFormat/></DataFormat><XMLElement dataType="character" isMappable="true" isNode="true" key="253" loopingOption="unique" maxOccurs="-1" minOccurs="0" name="item" typeExpanded="true" typeKey="165" typeName="BAPI_ITOB_SEL_STATUS" useNamespace="-1" validateData="false"><DataFormat><ProfileCharacterFormat/></DataFormat><XMLElement comments="範囲データ型の行データ型: タイプ SIGN のコンポーネント" dataType="character" isMappable="true" isNode="true" key="417" loopingOption="unique" maxLength="1" maxOccurs="1" minLength="0" minOccurs="0" name="SIGN" typeKey="-1" useNamespace="-1" validateData="true"><DataFormat><ProfileCharacterFormat/></DataFormat></XMLElement><XMLElement comments="範囲データ型の行データ型のタイプ OPTION のコンポーネント" dataType="character" isMappable="true" isNode="true" key="419" loopingOption="unique" maxLength="2" maxOccurs="1" minLength="0" minOccurs="0" name="OPTION" typeKey="-1" useNamespace="-1" validateData="true"><DataFormat><ProfileCharacterFormat/></DataFormat></XMLElement><XMLElement comments="オブジェクトの個別ステータス (簡略形式)" dataType="character" isMappable="true" isNode="true" key="421" loopingOption="unique" maxLength="4" maxOccurs="1" minLength="0" minOccurs="0" name="LOW" typeKey="-1" useNamespace="-1" validateData="true"><DataFormat><ProfileCharacterFormat/></DataFormat></XMLElement><XMLElement comments="オブジェクトの個別ステータス (簡略形式)" dataType="character" isMappable="true" isNode="true" key="423" loopingOption="unique" maxLength="4" maxOccurs="1" minLength="0" minOccurs="0" name="HIGH" typeKey="-1" useNamespace="-1" validateData="true"><DataFormat><ProfileCharacterFormat/></DataFormat></XMLElement></XMLElement></XMLElement><XMLElement comments="リターンパラメータ" dataType="character" isMappable="true" isNode="true" key="221" loopingOption="unique" maxOccurs="1" minOccurs="0" name="RETURN" typeExpanded="true" typeKey="172" typeName="BAPIRET2" useNamespace="-1" validateData="false"><DataFormat><ProfileCharacterFormat/></DataFormat><XMLElement comments="メッセージType: S 正常、E エラー、W 警告、I 通知、A 強制終了" dataType="character" isMappable="true" isNode="true" key="255" loopingOption="unique" maxLength="1" maxOccurs="1" minLength="0" minOccurs="0" name="TYPE" typeKey="-1" useNamespace="-1" validateData="true"><DataFormat><ProfileCharacterFormat/></DataFormat></XMLElement><XMLElement comments="メッセージクラス" dataType="character" isMappable="true" isNode="true" key="257" loopingOption="unique" maxLength="20" maxOccurs="1" minLength="0" minOccurs="0" name="ID" typeKey="-1" useNamespace="-1" validateData="true"><DataFormat><ProfileCharacterFormat/></DataFormat></XMLElement><XMLElement comments="メッセージ番号" dataType="number" isMappable="true" isNode="true" key="259" loopingOption="unique" maxOccurs="1" minOccurs="0" name="NUMBER" typeKey="-1" useNamespace="-1" validateData="false"><DataFormat><ProfileNumberFormat numberFormat=""/></DataFormat></XMLElement><XMLElement comments="メッセージテキスト" dataType="character" isMappable="true" isNode="true" key="261" loopingOption="unique" maxLength="220" maxOccurs="1" minLength="0" minOccurs="0" name="MESSAGE" typeKey="-1" useNamespace="-1" validateData="true"><DataFormat><ProfileCharacterFormat/></DataFormat></XMLElement><XMLElement comments="アプリケーションログ: ログ番号" dataType="character" isMappable="true" isNode="true" key="263" loopingOption="unique" maxLength="20" maxOccurs="1" minLength="0" minOccurs="0" name="LOG_NO" typeKey="-1" useNamespace="-1" validateData="true"><DataFormat><ProfileCharacterFormat/></DataFormat></XMLElement><XMLElement comments="アプリケーションログ: メッセージシリアル番号" dataType="number" isMappable="true" isNode="true" key="265" loopingOption="unique" maxOccurs="1" minOccurs="0" name="LOG_MSG_NO" typeKey="-1" useNamespace="-1" validateData="false"><DataFormat><ProfileNumberFormat numberFormat=""/></DataFormat></XMLElement><XMLElement comments="メッセージ変数" dataType="character" isMappable="true" isNode="true" key="267" loopingOption="unique" maxLength="50" maxOccurs="1" minLength="0" minOccurs="0" name="MESSAGE_V1" typeKey="-1" useNamespace="-1" validateData="true"><DataFormat><ProfileCharacterFormat/></DataFormat></XMLElement><XMLElement comments="メッセージ変数" dataType="character" isMappable="true" isNode="true" key="269" loopingOption="unique" maxLength="50" maxOccurs="1" minLength="0" minOccurs="0" name="MESSAGE_V2" typeKey="-1" useNamespace="-1" validateData="true"><DataFormat><ProfileCharacterFormat/></DataFormat></XMLElement><XMLElement comments="メッセージ変数" dataType="character" isMappable="true" isNode="true" key="271" loopingOption="unique" maxLength="50" maxOccurs="1" minLength="0" minOccurs="0" name="MESSAGE_V3" typeKey="-1" useNamespace="-1" validateData="true"><DataFormat><ProfileCharacterFormat/></DataFormat></XMLElement><XMLElement comments="メッセージ変数" dataType="character" isMappable="true" isNode="true" key="273" loopingOption="unique" maxLength="50" maxOccurs="1" minLength="0" minOccurs="0" name="MESSAGE_V4" typeKey="-1" useNamespace="-1" validateData="true"><DataFormat><ProfileCharacterFormat/></DataFormat></XMLElement><XMLElement comments="パラメータ名" dataType="character" isMappable="true" isNode="true" key="275" loopingOption="unique" maxLength="32" maxOccurs="1" minLength="0" minOccurs="0" name="PARAMETER" typeKey="-1" useNamespace="-1" validateData="true"><DataFormat><ProfileCharacterFormat/></DataFormat></XMLElement><XMLElement comments="パラメータの行" dataType="number" isMappable="true" isNode="true" key="277" loopingOption="unique" maxOccurs="1" minOccurs="0" name="ROW" typeKey="-1" useNamespace="-1" validateData="false"><DataFormat><ProfileNumberFormat numberFormat=""/></DataFormat></XMLElement><XMLElement comments="パラメータの項目" dataType="character" isMappable="true" isNode="true" key="279" loopingOption="unique" maxLength="30" maxOccurs="1" minLength="0" minOccurs="0" name="FIELD" typeKey="-1" useNamespace="-1" validateData="true"><DataFormat><ProfileCharacterFormat/></DataFormat></XMLElement><XMLElement comments="メッセージが発行された論理システム" dataType="character" isMappable="true" isNode="true" key="281" loopingOption="unique" maxLength="10" maxOccurs="1" minLength="0" minOccurs="0" name="SYSTEM" typeKey="-1" useNamespace="-1" validateData="true"><DataFormat><ProfileCharacterFormat/></DataFormat></XMLElement></XMLElement></XMLElement></DataElements><Namespaces><XMLNamespace key="-1" name="Empty Namespace" prefix="ns1"><Types><Type anonymous="true" declarationClass="cType" typeKey="-5"><XMLElement comments="BAPI Communication Structure: Range for Address City" dataType="character" isMappable="true" isNode="true" key="6" loopingOption="unique" maxOccurs="1" minOccurs="0" name="ADDRESS_CITY_RA" typeExpanded="false" typeKey="-5" useNamespace="-1" validateData="false"><DataFormat><ProfileCharacterFormat/></DataFormat><XMLElement dataType="character" isMappable="true" isNode="true" key="7" maxOccurs="-1" minOccurs="0" name="item" typeExpanded="false" typeKey="8" typeName="BAPI_ITOB_SEL_ADDR_CITY" useNamespace="-1"><DataFormat><ProfileCharacterFormat/></DataFormat></XMLElement></XMLElement></Type><Type anonymous="true" declarationClass="cType" typeKey="-15"><XMLElement comments="BAPI Communication Structure: Range for Address Name" dataType="character" isMappable="true" isNode="true" key="16" loopingOption="unique" maxOccurs="1" minOccurs="0" name="ADDRESS_NAME_RA" typeExpanded="false" typeKey="-15" useNamespace="-1" validateData="false"><DataFormat><ProfileCharacterFormat/></DataFormat><XMLElement dataType="character" isMappable="true" isNode="true" key="17" maxOccurs="-1" minOccurs="0" name="item" typeExpanded="false" typeKey="18" typeName="BAPI_ITOB_SEL_ADDR_NAME" useNamespace="-1"><DataFormat><ProfileCharacterFormat/></DataFormat></XMLElement></XMLElement></Type><Type anonymous="true" declarationClass="cType" typeKey="-25"><XMLElement comments="BAPI Communication Structure: Range for Address Postal Code" dataType="character" isMappable="true" isNode="true" key="26" loopingOption="unique" maxOccurs="1" minOccurs="0" name="ADDRESS_POST_CODE_RA" typeExpanded="false" typeKey="-25" useNamespace="-1" validateData="false"><DataFormat><ProfileCharacterFormat/></DataFormat><XMLElement dataType="character" isMappable="true" isNode="true" key="27" maxOccurs="-1" minOccurs="0" name="item" typeExpanded="false" typeKey="28" typeName="BAPI_ITOB_SEL_ADDR_POST_CODE" useNamespace="-1"><DataFormat><ProfileCharacterFormat/></DataFormat></XMLElement></XMLElement></Type><Type anonymous="true" declarationClass="cType" typeKey="-35"><XMLElement comments="BAPI Communication Structure: Range for Address Search Term 1" dataType="character" isMappable="true" isNode="true" key="36" loopingOption="unique" maxOccurs="1" minOccurs="0" name="ADDRESS_SEARCH_TERM_1_RA" typeExpanded="false" typeKey="-35" useNamespace="-1" validateData="false"><DataFormat><ProfileCharacterFormat/></DataFormat><XMLElement dataType="character" isMappable="true" isNode="true" key="37" maxOccurs="-1" minOccurs="0" name="item" typeExpanded="false" typeKey="38" typeName="BAPI_ITOB_SEL_ADDR_SORT1" useNamespace="-1"><DataFormat><ProfileCharacterFormat/></DataFormat></XMLElement></XMLElement></Type><Type anonymous="true" declarationClass="cType" typeKey="-45"><XMLElement comments="BAPI Communication Structure: Range for Address Search Term 2" dataType="character" isMappable="true" isNode="true" key="46" loopingOption="unique" maxOccurs="1" minOccurs="0" name="ADDRESS_SEARCH_TERM_2_RA" typeExpanded="false" typeKey="-45" useNamespace="-1" validateData="false"><DataFormat><ProfileCharacterFormat/></DataFormat><XMLElement dataType="character" isMappable="true" isNode="true" key="47" maxOccurs="-1" minOccurs="0" name="item" typeExpanded="false" typeKey="48" typeName="BAPI_ITOB_SEL_ADDR_SORT2" useNamespace="-1"><DataFormat><ProfileCharacterFormat/></DataFormat></XMLElement></XMLElement></Type><Type anonymous="true" declarationClass="cType" typeKey="-55"><XMLElement comments="BAPI Communication Structure: Range for Address Street" dataType="character" isMappable="true" isNode="true" key="56" loopingOption="unique" maxOccurs="1" minOccurs="0" name="ADDRESS_STREET_RA" typeExpanded="false" typeKey="-55" useNamespace="-1" validateData="false"><DataFormat><ProfileCharacterFormat/></DataFormat><XMLElement dataType="character" isMappable="true" isNode="true" key="57" maxOccurs="-1" minOccurs="0" name="item" typeExpanded="false" typeKey="58" typeName="BAPI_ITOB_SEL_ADDR_STREET" useNamespace="-1"><DataFormat><ProfileCharacterFormat/></DataFormat></XMLElement></XMLElement></Type><Type anonymous="true" declarationClass="cType" typeKey="-2"><XMLElement dataType="character" isMappable="true" isNode="true" key="3" loopingOption="unique" maxOccurs="1" minOccurs="0" name="BAPI_FUNCLOC_GETLIST" typeExpanded="false" typeKey="-2" useNamespace="-1" validateData="false"><DataFormat><ProfileCharacterFormat/></DataFormat><XMLElement comments="BAPI Communication Structure: Range for Address City" dataType="character" isMappable="true" isNode="true" key="4" maxOccurs="1" minOccurs="0" name="ADDRESS_CITY_RA" typeExpanded="false" typeKey="-5" useNamespace="-1"><DataFormat><ProfileCharacterFormat/></DataFormat></XMLElement><XMLElement comments="BAPI Communication Structure: Range for Address Name" dataType="character" isMappable="true" isNode="true" key="14" maxOccurs="1" minOccurs="0" name="ADDRESS_NAME_RA" typeExpanded="false" typeKey="-15" useNamespace="-1"><DataFormat><ProfileCharacterFormat/></DataFormat></XMLElement><XMLElement comments="BAPI Communication Structure: Range for Address Postal Code" dataType="character" isMappable="true" isNode="true" key="24" maxOccurs="1" minOccurs="0" name="ADDRESS_POST_CODE_RA" typeExpanded="false" typeKey="-25" useNamespace="-1"><DataFormat><ProfileCharacterFormat/></DataFormat></XMLElement><XMLElement comments="BAPI Communication Structure: Range for Address Search Term 1" dataType="character" isMappable="true" isNode="true" key="34" maxOccurs="1" minOccurs="0" name="ADDRESS_SEARCH_TERM_1_RA" typeExpanded="false" typeKey="-35" useNamespace="-1"><DataFormat><ProfileCharacterFormat/></DataFormat></XMLElement><XMLElement comments="BAPI Communication Structure: Range for Address Search Term 2" dataType="character" isMappable="true" isNode="true" key="44" maxOccurs="1" minOccurs="0" name="ADDRESS_SEARCH_TERM_2_RA" typeExpanded="false" typeKey="-45" useNamespace="-1"><DataFormat><ProfileCharacterFormat/></DataFormat></XMLElement><XMLElement comments="BAPI Communication Structure: Range for Address Street" dataType="character" isMappable="true" isNode="true" key="54" maxOccurs="1" minOccurs="0" name="ADDRESS_STREET_RA" typeExpanded="false" typeKey="-55" useNamespace="-1"><DataFormat><ProfileCharacterFormat/></DataFormat></XMLElement><XMLElement comments="BAPI 通信構造: テキストの範囲" dataType="character" isMappable="true" isNode="true" key="64" maxOccurs="1" minOccurs="0" name="DESCRIPT_RA" typeExpanded="false" typeKey="-65" useNamespace="-1"><DataFormat><ProfileCharacterFormat/></DataFormat></XMLElement><XMLElement comments="BAPI 通信構造: 選択結果一覧" dataType="character" isMappable="true" isNode="true" key="74" maxOccurs="1" minOccurs="1" name="FUNCLOC_LIST" typeExpanded="false" typeKey="-75" useNamespace="-1"><DataFormat><ProfileCharacterFormat/></DataFormat></XMLElement><XMLElement comments="BAPI 通信構造: 機能場所の範囲" dataType="character" isMappable="true" isNode="true" key="91" maxOccurs="1" minOccurs="0" name="FUNCLOC_RA" typeExpanded="false" typeKey="-92" useNamespace="-1"><DataFormat><ProfileCharacterFormat/></DataFormat></XMLElement><XMLElement comments="BAPI 通信構造: 保全プラントの範囲" dataType="character" isMappable="true" isNode="true" key="101" maxOccurs="1" minOccurs="0" name="MAINTPLANT_RA" typeExpanded="false" typeKey="-102" useNamespace="-1"><DataFormat><ProfileCharacterFormat/></DataFormat></XMLElement><XMLElement comments="BAPI Communication Structure: Range for Object Type" dataType="character" isMappable="true" isNode="true" key="111" maxOccurs="1" minOccurs="0" name="OBJECTTYPE_RA" typeExpanded="false" typeKey="-112" useNamespace="-1"><DataFormat><ProfileCharacterFormat/></DataFormat></XMLElement><XMLElement comments="BAPI Communication Structure: Range for Partner" dataType="character" isMappable="true" isNode="true" key="121" maxOccurs="1" minOccurs="0" name="PARTNER_RA" typeExpanded="false" typeKey="-122" useNamespace="-1"><DataFormat><ProfileCharacterFormat/></DataFormat></XMLElement><XMLElement comments="BAPI 通信構造: 保全計画グループの範囲" dataType="character" isMappable="true" isNode="true" key="131" maxOccurs="1" minOccurs="0" name="PLANGROUP_RA" typeExpanded="false" typeKey="-132" useNamespace="-1"><DataFormat><ProfileCharacterFormat/></DataFormat></XMLElement><XMLElement comments="BAPI 通信構造: 保全計画の範囲" dataType="character" isMappable="true" isNode="true" key="141" maxOccurs="1" minOccurs="0" name="PLANPLANT_RA" typeExpanded="false" typeKey="-142" useNamespace="-1"><DataFormat><ProfileCharacterFormat/></DataFormat></XMLElement><XMLElement comments="BAPI 通信構造: ソート項目の範囲" dataType="character" isMappable="true" isNode="true" key="151" maxOccurs="1" minOccurs="0" name="SORTFIELD_RA" typeExpanded="false" typeKey="-152" useNamespace="-1"><DataFormat><ProfileCharacterFormat/></DataFormat></XMLElement><XMLElement comments="BAPI Communication Structure: Range for Status" dataType="character" isMappable="true" isNode="true" key="161" maxOccurs="1" minOccurs="0" name="STATUS_RA" typeExpanded="false" typeKey="-162" useNamespace="-1"><DataFormat><ProfileCharacterFormat/></DataFormat></XMLElement><XMLElement comments="リターンパラメータ" dataType="character" isMappable="true" isNode="true" key="171" maxOccurs="1" minOccurs="0" name="RETURN" typeExpanded="false" typeKey="172" typeName="BAPIRET2" useNamespace="-1"><DataFormat><ProfileCharacterFormat/></DataFormat></XMLElement></XMLElement></Type><Type anonymous="false" declarationClass="cType" typeKey="78"><XMLElement dataType="character" isMappable="true" isNode="true" key="79" loopingOption="unique" maxOccurs="-1" minOccurs="0" name="BAPI_ITOB_FL_SEL_RESULT" typeExpanded="false" typeKey="78" typeName="BAPI_ITOB_FL_SEL_RESULT" useNamespace="-1" validateData="false"><DataFormat><ProfileCharacterFormat/></DataFormat><XMLElement comments="機能場所" dataType="character" isMappable="true" isNode="true" key="80" maxLength="30" maxOccurs="1" minLength="0" minOccurs="0" name="FUNCTLOCATION" useNamespace="-1" validateData="true"><DataFormat><ProfileCharacterFormat/></DataFormat></XMLElement><XMLElement comments="機能場所ラベル" dataType="character" isMappable="true" isNode="true" key="81" maxLength="40" maxOccurs="1" minLength="0" minOccurs="0" name="FUNCLOC" useNamespace="-1" validateData="true"><DataFormat><ProfileCharacterFormat/></DataFormat></XMLElement><XMLElement comments="機能場所のラベルシステム" dataType="character" isMappable="true" isNode="true" key="82" maxLength="1" maxOccurs="1" minLength="0" minOccurs="0" name="LABEL_SYST" useNamespace="-1" validateData="true"><DataFormat><ProfileCharacterFormat/></DataFormat></XMLElement><XMLElement comments="技術対象テキスト" dataType="character" isMappable="true" isNode="true" key="83" maxLength="40" maxOccurs="1" minLength="0" minOccurs="0" name="DESCRIPT" useNamespace="-1" validateData="true"><DataFormat><ProfileCharacterFormat/></DataFormat></XMLElement><XMLElement comments="機能場所構成区分" dataType="character" isMappable="true" isNode="true" key="84" maxLength="5" maxOccurs="1" minLength="0" minOccurs="0" name="STRIND" useNamespace="-1" validateData="true"><DataFormat><ProfileCharacterFormat/></DataFormat></XMLElement><XMLElement comments="機能場所カテゴリ" dataType="character" isMappable="true" isNode="true" key="85" maxLength="1" maxOccurs="1" minLength="0" minOccurs="0" name="CATEGORY" useNamespace="-1" validateData="true"><DataFormat><ProfileCharacterFormat/></DataFormat></XMLElement><XMLElement comments="上位機能場所" dataType="character" isMappable="true" isNode="true" key="86" maxLength="30" maxOccurs="1" minLength="0" minOccurs="0" name="SUPFLOC" useNamespace="-1" validateData="true"><DataFormat><ProfileCharacterFormat/></DataFormat></XMLElement><XMLElement comments="保全計画プラント" dataType="character" isMappable="true" isNode="true" key="87" maxLength="4" maxOccurs="1" minLength="0" minOccurs="0" name="PLANPLANT" useNamespace="-1" validateData="true"><DataFormat><ProfileCharacterFormat/></DataFormat></XMLElement><XMLElement comments="保全プラント" dataType="character" isMappable="true" isNode="true" key="88" maxLength="4" maxOccurs="1" minLength="0" minOccurs="0" name="MAINTPLANT" useNamespace="-1" validateData="true"><DataFormat><ProfileCharacterFormat/></DataFormat></XMLElement><XMLElement comments="得意先サービスおよびプラント保全の計画グループ" dataType="character" isMappable="true" isNode="true" key="89" maxLength="3" maxOccurs="1" minLength="0" minOccurs="0" name="PLANGROUP" useNamespace="-1" validateData="true"><DataFormat><ProfileCharacterFormat/></DataFormat></XMLElement><XMLElement comments="ソート項目" dataType="character" isMappable="true" isNode="true" key="90" maxLength="30" maxOccurs="1" minLength="0" minOccurs="0" name="SORTFIELD" useNamespace="-1" validateData="true"><DataFormat><ProfileCharacterFormat/></DataFormat></XMLElement></XMLElement></Type><Type anonymous="false" declarationClass="cType" typeKey="8"><XMLElement dataType="character" isMappable="true" isNode="true" key="9" loopingOption="unique" maxOccurs="-1" minOccurs="0" name="BAPI_ITOB_SEL_ADDR_CITY" typeExpanded="false" typeKey="8" typeName="BAPI_ITOB_SEL_ADDR_CITY" useNamespace="-1" validateData="false"><DataFormat><ProfileCharacterFormat/></DataFormat><XMLElement comments="範囲データ型の行データ型: タイプ SIGN のコンポーネント" dataType="character" isMappable="true" isNode="true" key="10" maxLength="1" maxOccurs="1" minLength="0" minOccurs="0" name="SIGN" useNamespace="-1" validateData="true"><DataFormat><ProfileCharacterFormat/></DataFormat></XMLElement><XMLElement comments="範囲データ型の行データ型のタイプ OPTION のコンポーネント" dataType="character" isMappable="true" isNode="true" key="11" maxLength="2" maxOccurs="1" minLength="0" minOccurs="0" name="OPTION" useNamespace="-1" validateData="true"><DataFormat><ProfileCharacterFormat/></DataFormat></XMLElement><XMLElement comments="検索ヘルプ用大文字の市区町村名" dataType="character" isMappable="true" isNode="true" key="12" maxLength="25" maxOccurs="1" minLength="0" minOccurs="0" name="LOW" useNamespace="-1" validateData="true"><DataFormat><ProfileCharacterFormat/></DataFormat></XMLElement><XMLElement comments="検索ヘルプ用大文字の市区町村名" dataType="character" isMappable="true" isNode="true" key="13" maxLength="25" maxOccurs="1" minLength="0" minOccurs="0" name="HIGH" useNamespace="-1" validateData="true"><DataFormat><ProfileCharacterFormat/></DataFormat></XMLElement></XMLElement></Type><Type anonymous="false" declarationClass="cType" typeKey="18"><XMLElement dataType="character" isMappable="true" isNode="true" key="19" loopingOption="unique" maxOccurs="-1" minOccurs="0" name="BAPI_ITOB_SEL_ADDR_NAME" typeExpanded="false" typeKey="18" typeName="BAPI_ITOB_SEL_ADDR_NAME" useNamespace="-1" validateData="false"><DataFormat><ProfileCharacterFormat/></DataFormat><XMLElement comments="範囲データ型の行データ型: タイプ SIGN のコンポーネント" dataType="character" isMappable="true" isNode="true" key="20" maxLength="1" maxOccurs="1" minLength="0" minOccurs="0" name="SIGN" useNamespace="-1" validateData="true"><DataFormat><ProfileCharacterFormat/></DataFormat></XMLElement><XMLElement comments="範囲データ型の行データ型のタイプ OPTION のコンポーネント" dataType="character" isMappable="true" isNode="true" key="21" maxLength="2" maxOccurs="1" minLength="0" minOccurs="0" name="OPTION" useNamespace="-1" validateData="true"><DataFormat><ProfileCharacterFormat/></DataFormat></XMLElement><XMLElement comments="マッチコード用大文字の名称 (項目 NAME1)" dataType="character" isMappable="true" isNode="true" key="22" maxLength="25" maxOccurs="1" minLength="0" minOccurs="0" name="LOW" useNamespace="-1" validateData="true"><DataFormat><ProfileCharacterFormat/></DataFormat></XMLElement><XMLElement comments="マッチコード用大文字の名称 (項目 NAME1)" dataType="character" isMappable="true" isNode="true" key="23" maxLength="25" maxOccurs="1" minLength="0" minOccurs="0" name="HIGH" useNamespace="-1" validateData="true"><DataFormat><ProfileCharacterFormat/></DataFormat></XMLElement></XMLElement></Type><Type anonymous="false" declarationClass="cType" typeKey="28"><XMLElement dataType="character" isMappable="true" isNode="true" key="29" loopingOption="unique" maxOccurs="-1" minOccurs="0" name="BAPI_ITOB_SEL_ADDR_POST_CODE" typeExpanded="false" typeKey="28" typeName="BAPI_ITOB_SEL_ADDR_POST_CODE" useNamespace="-1" validateData="false"><DataFormat><ProfileCharacterFormat/></DataFormat><XMLElement comments="範囲データ型の行データ型: タイプ SIGN のコンポーネント" dataType="character" isMappable="true" isNode="true" key="30" maxLength="1" maxOccurs="1" minLength="0" minOccurs="0" name="SIGN" useNamespace="-1" validateData="true"><DataFormat><ProfileCharacterFormat/></DataFormat></XMLElement><XMLElement comments="範囲データ型の行データ型のタイプ OPTION のコンポーネント" dataType="character" isMappable="true" isNode="true" key="31" maxLength="2" maxOccurs="1" minLength="0" minOccurs="0" name="OPTION" useNamespace="-1" validateData="true"><DataFormat><ProfileCharacterFormat/></DataFormat></XMLElement><XMLElement comments="市区町村の郵便番号" dataType="character" isMappable="true" isNode="true" key="32" maxLength="10" maxOccurs="1" minLength="0" minOccurs="0" name="LOW" useNamespace="-1" validateData="true"><DataFormat><ProfileCharacterFormat/></DataFormat></XMLElement><XMLElement comments="市区町村の郵便番号" dataType="character" isMappable="true" isNode="true" key="33" maxLength="10" maxOccurs="1" minLength="0" minOccurs="0" name="HIGH" useNamespace="-1" validateData="true"><DataFormat><ProfileCharacterFormat/></DataFormat></XMLElement></XMLElement></Type><Type anonymous="false" declarationClass="cType" typeKey="38"><XMLElement dataType="character" isMappable="true" isNode="true" key="39" loopingOption="unique" maxOccurs="-1" minOccurs="0" name="BAPI_ITOB_SEL_ADDR_SORT1" typeExpanded="false" typeKey="38" typeName="BAPI_ITOB_SEL_ADDR_SORT1" useNamespace="-1" validateData="false"><DataFormat><ProfileCharacterFormat/></DataFormat><XMLElement comments="範囲データ型の行データ型: タイプ SIGN のコンポーネント" dataType="character" isMappable="true" isNode="true" key="40" maxLength="1" maxOccurs="1" minLength="0" minOccurs="0" name="SIGN" useNamespace="-1" validateData="true"><DataFormat><ProfileCharacterFormat/></DataFormat></XMLElement><XMLElement comments="範囲データ型の行データ型のタイプ OPTION のコンポーネント" dataType="character" isMappable="true" isNode="true" key="41" maxLength="2" maxOccurs="1" minLength="0" minOccurs="0" name="OPTION" useNamespace="-1" validateData="true"><DataFormat><ProfileCharacterFormat/></DataFormat></XMLElement><XMLElement comments="検索語句 1" dataType="character" isMappable="true" isNode="true" key="42" maxLength="20" maxOccurs="1" minLength="0" minOccurs="0" name="LOW" useNamespace="-1" validateData="true"><DataFormat><ProfileCharacterFormat/></DataFormat></XMLElement><XMLElement comments="検索語句 1" dataType="character" isMappable="true" isNode="true" key="43" maxLength="20" maxOccurs="1" minLength="0" minOccurs="0" name="HIGH" useNamespace="-1" validateData="true"><DataFormat><ProfileCharacterFormat/></DataFormat></XMLElement></XMLElement></Type><Type anonymous="false" declarationClass="cType" typeKey="48"><XMLElement dataType="character" isMappable="true" isNode="true" key="49" loopingOption="unique" maxOccurs="-1" minOccurs="0" name="BAPI_ITOB_SEL_ADDR_SORT2" typeExpanded="false" typeKey="48" typeName="BAPI_ITOB_SEL_ADDR_SORT2" useNamespace="-1" validateData="false"><DataFormat><ProfileCharacterFormat/></DataFormat><XMLElement comments="範囲データ型の行データ型: タイプ SIGN のコンポーネント" dataType="character" isMappable="true" isNode="true" key="50" maxLength="1" maxOccurs="1" minLength="0" minOccurs="0" name="SIGN" useNamespace="-1" validateData="true"><DataFormat><ProfileCharacterFormat/></DataFormat></XMLElement><XMLElement comments="範囲データ型の行データ型のタイプ OPTION のコンポーネント" dataType="character" isMappable="true" isNode="true" key="51" maxLength="2" maxOccurs="1" minLength="0" minOccurs="0" name="OPTION" useNamespace="-1" validateData="true"><DataFormat><ProfileCharacterFormat/></DataFormat></XMLElement><XMLElement comments="検索語句 2" dataType="character" isMappable="true" isNode="true" key="52" maxLength="20" maxOccurs="1" minLength="0" minOccurs="0" name="LOW" useNamespace="-1" validateData="true"><DataFormat><ProfileCharacterFormat/></DataFormat></XMLElement><XMLElement comments="検索語句 2" dataType="character" isMappable="true" isNode="true" key="53" maxLength="20" maxOccurs="1" minLength="0" minOccurs="0" name="HIGH" useNamespace="-1" validateData="true"><DataFormat><ProfileCharacterFormat/></DataFormat></XMLElement></XMLElement></Type><Type anonymous="false" declarationClass="cType" typeKey="58"><XMLElement dataType="character" isMappable="true" isNode="true" key="59" loopingOption="unique" maxOccurs="-1" minOccurs="0" name="BAPI_ITOB_SEL_ADDR_STREET" typeExpanded="false" typeKey="58" typeName="BAPI_ITOB_SEL_ADDR_STREET" useNamespace="-1" validateData="false"><DataFormat><ProfileCharacterFormat/></DataFormat><XMLElement comments="範囲データ型の行データ型: タイプ SIGN のコンポーネント" dataType="character" isMappable="true" isNode="true" key="60" maxLength="1" maxOccurs="1" minLength="0" minOccurs="0" name="SIGN" useNamespace="-1" validateData="true"><DataFormat><ProfileCharacterFormat/></DataFormat></XMLElement><XMLElement comments="範囲データ型の行データ型のタイプ OPTION のコンポーネント" dataType="character" isMappable="true" isNode="true" key="61" maxLength="2" maxOccurs="1" minLength="0" minOccurs="0" name="OPTION" useNamespace="-1" validateData="true"><DataFormat><ProfileCharacterFormat/></DataFormat></XMLElement><XMLElement comments="検索ヘルプ用大文字の地名" dataType="character" isMappable="true" isNode="true" key="62" maxLength="25" maxOccurs="1" minLength="0" minOccurs="0" name="LOW" useNamespace="-1" validateData="true"><DataFormat><ProfileCharacterFormat/></DataFormat></XMLElement><XMLElement comments="検索ヘルプ用大文字の地名" dataType="character" isMappable="true" isNode="true" key="63" maxLength="25" maxOccurs="1" minLength="0" minOccurs="0" name="HIGH" useNamespace="-1" validateData="true"><DataFormat><ProfileCharacterFormat/></DataFormat></XMLElement></XMLElement></Type><Type anonymous="false" declarationClass="cType" typeKey="68"><XMLElement dataType="character" isMappable="true" isNode="true" key="69" loopingOption="unique" maxOccurs="-1" minOccurs="0" name="BAPI_ITOB_SEL_DESCRIPT" typeExpanded="false" typeKey="68" typeName="BAPI_ITOB_SEL_DESCRIPT" useNamespace="-1" validateData="false"><DataFormat><ProfileCharacterFormat/></DataFormat><XMLElement comments="選択演算子 SIGN (テーブル範囲)" dataType="character" isMappable="true" isNode="true" key="70" maxLength="1" maxOccurs="1" minLength="0" minOccurs="0" name="SIGN" useNamespace="-1" validateData="true"><DataFormat><ProfileCharacterFormat/></DataFormat></XMLElement><XMLElement comments="選択演算子 OPTION (範囲テーブル)" dataType="character" isMappable="true" isNode="true" key="71" maxLength="2" maxOccurs="1" minLength="0" minOccurs="0" name="OPTION" useNamespace="-1" validateData="true"><DataFormat><ProfileCharacterFormat/></DataFormat></XMLElement><XMLElement comments="技術対象テキスト" dataType="character" isMappable="true" isNode="true" key="72" maxLength="40" maxOccurs="1" minLength="0" minOccurs="0" name="LOW" useNamespace="-1" validateData="true"><DataFormat><ProfileCharacterFormat/></DataFormat></XMLElement><XMLElement comments="技術対象テキスト" dataType="character" isMappable="true" isNode="true" key="73" maxLength="40" maxOccurs="1" minLength="0" minOccurs="0" name="HIGH" useNamespace="-1" validateData="true"><DataFormat><ProfileCharacterFormat/></DataFormat></XMLElement></XMLElement></Type><Type anonymous="false" declarationClass="cType" typeKey="95"><XMLElement dataType="character" isMappable="true" isNode="true" key="96" loopingOption="unique" maxOccurs="-1" minOccurs="0" name="BAPI_ITOB_SEL_FUNCLOC" typeExpanded="false" typeKey="95" typeName="BAPI_ITOB_SEL_FUNCLOC" useNamespace="-1" validateData="false"><DataFormat><ProfileCharacterFormat/></DataFormat><XMLElement comments="選択演算子 SIGN (テーブル範囲)" dataType="character" isMappable="true" isNode="true" key="97" maxLength="1" maxOccurs="1" minLength="0" minOccurs="0" name="SIGN" useNamespace="-1" validateData="true"><DataFormat><ProfileCharacterFormat/></DataFormat></XMLElement><XMLElement comments="選択演算子 OPTION (範囲テーブル)" dataType="character" isMappable="true" isNode="true" key="98" maxLength="2" maxOccurs="1" minLength="0" minOccurs="0" name="OPTION" useNamespace="-1" validateData="true"><DataFormat><ProfileCharacterFormat/></DataFormat></XMLElement><XMLElement comments="機能場所ラベル" dataType="character" isMappable="true" isNode="true" key="99" maxLength="40" maxOccurs="1" minLength="0" minOccurs="0" name="LOW" useNamespace="-1" validateData="true"><DataFormat><ProfileCharacterFormat/></DataFormat></XMLElement><XMLElement comments="機能場所ラベル" dataType="character" isMappable="true" isNode="true" key="100" maxLength="40" maxOccurs="1" minLength="0" minOccurs="0" name="HIGH" useNamespace="-1" validateData="true"><DataFormat><ProfileCharacterFormat/></DataFormat></XMLElement></XMLElement></Type><Type anonymous="false" declarationClass="cType" typeKey="105"><XMLElement dataType="character" isMappable="true" isNode="true" key="106" loopingOption="unique" maxOccurs="-1" minOccurs="0" name="BAPI_ITOB_SEL_MAINTPLANT" typeExpanded="false" typeKey="105" typeName="BAPI_ITOB_SEL_MAINTPLANT" useNamespace="-1" validateData="false"><DataFormat><ProfileCharacterFormat/></DataFormat><XMLElement comments="選択演算子 SIGN (テーブル範囲)" dataType="character" isMappable="true" isNode="true" key="107" maxLength="1" maxOccurs="1" minLength="0" minOccurs="0" name="SIGN" useNamespace="-1" validateData="true"><DataFormat><ProfileCharacterFormat/></DataFormat></XMLElement><XMLElement comments="選択演算子 OPTION (範囲テーブル)" dataType="character" isMappable="true" isNode="true" key="108" maxLength="2" maxOccurs="1" minLength="0" minOccurs="0" name="OPTION" useNamespace="-1" validateData="true"><DataFormat><ProfileCharacterFormat/></DataFormat></XMLElement><XMLElement comments="保全プラント" dataType="character" isMappable="true" isNode="true" key="109" maxLength="4" maxOccurs="1" minLength="0" minOccurs="0" name="LOW" useNamespace="-1" validateData="true"><DataFormat><ProfileCharacterFormat/></DataFormat></XMLElement><XMLElement comments="保全プラント" dataType="character" isMappable="true" isNode="true" key="110" maxLength="4" maxOccurs="1" minLength="0" minOccurs="0" name="HIGH" useNamespace="-1" validateData="true"><DataFormat><ProfileCharacterFormat/></DataFormat></XMLElement></XMLElement></Type><Type anonymous="false" declarationClass="cType" typeKey="115"><XMLElement dataType="character" isMappable="true" isNode="true" key="116" loopingOption="unique" maxOccurs="-1" minOccurs="0" name="BAPI_ITOB_SEL_OBJECTTYPE" typeExpanded="false" typeKey="115" typeName="BAPI_ITOB_SEL_OBJECTTYPE" useNamespace="-1" validateData="false"><DataFormat><ProfileCharacterFormat/></DataFormat><XMLElement comments="範囲データ型の行データ型: タイプ SIGN のコンポーネント" dataType="character" isMappable="true" isNode="true" key="117" maxLength="1" maxOccurs="1" minLength="0" minOccurs="0" name="SIGN" useNamespace="-1" validateData="true"><DataFormat><ProfileCharacterFormat/></DataFormat></XMLElement><XMLElement comments="範囲データ型の行データ型のタイプ OPTION のコンポーネント" dataType="character" isMappable="true" isNode="true" key="118" maxLength="2" maxOccurs="1" minLength="0" minOccurs="0" name="OPTION" useNamespace="-1" validateData="true"><DataFormat><ProfileCharacterFormat/></DataFormat></XMLElement><XMLElement comments="技術対象タイプ" dataType="character" isMappable="true" isNode="true" key="119" maxLength="10" maxOccurs="1" minLength="0" minOccurs="0" name="LOW" useNamespace="-1" validateData="true"><DataFormat><ProfileCharacterFormat/></DataFormat></XMLElement><XMLElement comments="技術対象タイプ" dataType="character" isMappable="true" isNode="true" key="120" maxLength="10" maxOccurs="1" minLength="0" minOccurs="0" name="HIGH" useNamespace="-1" validateData="true"><DataFormat><ProfileCharacterFormat/></DataFormat></XMLElement></XMLElement></Type><Type anonymous="false" declarationClass="cType" typeKey="125"><XMLElement dataType="character" isMappable="true" isNode="true" key="126" loopingOption="unique" maxOccurs="-1" minOccurs="0" name="BAPI_ITOB_SEL_PARTNER" typeExpanded="false" typeKey="125" typeName="BAPI_ITOB_SEL_PARTNER" useNamespace="-1" validateData="false"><DataFormat><ProfileCharacterFormat/></DataFormat><XMLElement comments="範囲データ型の行データ型: タイプ SIGN のコンポーネント" dataType="character" isMappable="true" isNode="true" key="127" maxLength="1" maxOccurs="1" minLength="0" minOccurs="0" name="SIGN" useNamespace="-1" validateData="true"><DataFormat><ProfileCharacterFormat/></DataFormat></XMLElement><XMLElement comments="範囲データ型の行データ型のタイプ OPTION のコンポーネント" dataType="character" isMappable="true" isNode="true" key="128" maxLength="2" maxOccurs="1" minLength="0" minOccurs="0" name="OPTION" useNamespace="-1" validateData="true"><DataFormat><ProfileCharacterFormat/></DataFormat></XMLElement><XMLElement comments="パートナ" dataType="character" isMappable="true" isNode="true" key="129" maxLength="12" maxOccurs="1" minLength="0" minOccurs="0" name="LOW" useNamespace="-1" validateData="true"><DataFormat><ProfileCharacterFormat/></DataFormat></XMLElement><XMLElement comments="パートナ" dataType="character" isMappable="true" isNode="true" key="130" maxLength="12" maxOccurs="1" minLength="0" minOccurs="0" name="HIGH" useNamespace="-1" validateData="true"><DataFormat><ProfileCharacterFormat/></DataFormat></XMLElement></XMLElement></Type><Type anonymous="false" declarationClass="cType" typeKey="135"><XMLElement dataType="character" isMappable="true" isNode="true" key="136" loopingOption="unique" maxOccurs="-1" minOccurs="0" name="BAPI_ITOB_SEL_PLANGROUP" typeExpanded="false" typeKey="135" typeName="BAPI_ITOB_SEL_PLANGROUP" useNamespace="-1" validateData="false"><DataFormat><ProfileCharacterFormat/></DataFormat><XMLElement comments="選択演算子 SIGN (テーブル範囲)" dataType="character" isMappable="true" isNode="true" key="137" maxLength="1" maxOccurs="1" minLength="0" minOccurs="0" name="SIGN" useNamespace="-1" validateData="true"><DataFormat><ProfileCharacterFormat/></DataFormat></XMLElement><XMLElement comments="選択演算子 OPTION (範囲テーブル)" dataType="character" isMappable="true" isNode="true" key="138" maxLength="2" maxOccurs="1" minLength="0" minOccurs="0" name="OPTION" useNamespace="-1" validateData="true"><DataFormat><ProfileCharacterFormat/></DataFormat></XMLElement><XMLElement comments="得意先サービスおよびプラント保全の計画グループ" dataType="character" isMappable="true" isNode="true" key="139" maxLength="3" maxOccurs="1" minLength="0" minOccurs="0" name="LOW" useNamespace="-1" validateData="true"><DataFormat><ProfileCharacterFormat/></DataFormat></XMLElement><XMLElement comments="得意先サービスおよびプラント保全の計画グループ" dataType="character" isMappable="true" isNode="true" key="140" maxLength="3" maxOccurs="1" minLength="0" minOccurs="0" name="HIGH" useNamespace="-1" validateData="true"><DataFormat><ProfileCharacterFormat/></DataFormat></XMLElement></XMLElement></Type><Type anonymous="false" declarationClass="cType" typeKey="145"><XMLElement dataType="character" isMappable="true" isNode="true" key="146" loopingOption="unique" maxOccurs="-1" minOccurs="0" name="BAPI_ITOB_SEL_PLANPLANT" typeExpanded="false" typeKey="145" typeName="BAPI_ITOB_SEL_PLANPLANT" useNamespace="-1" validateData="false"><DataFormat><ProfileCharacterFormat/></DataFormat><XMLElement comments="選択演算子 SIGN (テーブル範囲)" dataType="character" isMappable="true" isNode="true" key="147" maxLength="1" maxOccurs="1" minLength="0" minOccurs="0" name="SIGN" useNamespace="-1" validateData="true"><DataFormat><ProfileCharacterFormat/></DataFormat></XMLElement><XMLElement comments="選択演算子 OPTION (範囲テーブル)" dataType="character" isMappable="true" isNode="true" key="148" maxLength="2" maxOccurs="1" minLength="0" minOccurs="0" name="OPTION" useNamespace="-1" validateData="true"><DataFormat><ProfileCharacterFormat/></DataFormat></XMLElement><XMLElement comments="保全計画プラント" dataType="character" isMappable="true" isNode="true" key="149" maxLength="4" maxOccurs="1" minLength="0" minOccurs="0" name="LOW" useNamespace="-1" validateData="true"><DataFormat><ProfileCharacterFormat/></DataFormat></XMLElement><XMLElement comments="保全計画プラント" dataType="character" isMappable="true" isNode="true" key="150" maxLength="4" maxOccurs="1" minLength="0" minOccurs="0" name="HIGH" useNamespace="-1" validateData="true"><DataFormat><ProfileCharacterFormat/></DataFormat></XMLElement></XMLElement></Type><Type anonymous="false" declarationClass="cType" typeKey="155"><XMLElement dataType="character" isMappable="true" isNode="true" key="156" loopingOption="unique" maxOccurs="-1" minOccurs="0" name="BAPI_ITOB_SEL_SORTFIELD" typeExpanded="false" typeKey="155" typeName="BAPI_ITOB_SEL_SORTFIELD" useNamespace="-1" validateData="false"><DataFormat><ProfileCharacterFormat/></DataFormat><XMLElement comments="選択演算子 SIGN (テーブル範囲)" dataType="character" isMappable="true" isNode="true" key="157" maxLength="1" maxOccurs="1" minLength="0" minOccurs="0" name="SIGN" useNamespace="-1" validateData="true"><DataFormat><ProfileCharacterFormat/></DataFormat></XMLElement><XMLElement comments="選択演算子 OPTION (範囲テーブル)" dataType="character" isMappable="true" isNode="true" key="158" maxLength="2" maxOccurs="1" minLength="0" minOccurs="0" name="OPTION" useNamespace="-1" validateData="true"><DataFormat><ProfileCharacterFormat/></DataFormat></XMLElement><XMLElement comments="ソート項目" dataType="character" isMappable="true" isNode="true" key="159" maxLength="30" maxOccurs="1" minLength="0" minOccurs="0" name="LOW" useNamespace="-1" validateData="true"><DataFormat><ProfileCharacterFormat/></DataFormat></XMLElement><XMLElement comments="ソート項目" dataType="character" isMappable="true" isNode="true" key="160" maxLength="30" maxOccurs="1" minLength="0" minOccurs="0" name="HIGH" useNamespace="-1" validateData="true"><DataFormat><ProfileCharacterFormat/></DataFormat></XMLElement></XMLElement></Type><Type anonymous="false" declarationClass="cType" typeKey="165"><XMLElement dataType="character" isMappable="true" isNode="true" key="166" loopingOption="unique" maxOccurs="-1" minOccurs="0" name="BAPI_ITOB_SEL_STATUS" typeExpanded="false" typeKey="165" typeName="BAPI_ITOB_SEL_STATUS" useNamespace="-1" validateData="false"><DataFormat><ProfileCharacterFormat/></DataFormat><XMLElement comments="範囲データ型の行データ型: タイプ SIGN のコンポーネント" dataType="character" isMappable="true" isNode="true" key="167" maxLength="1" maxOccurs="1" minLength="0" minOccurs="0" name="SIGN" useNamespace="-1" validateData="true"><DataFormat><ProfileCharacterFormat/></DataFormat></XMLElement><XMLElement comments="範囲データ型の行データ型のタイプ OPTION のコンポーネント" dataType="character" isMappable="true" isNode="true" key="168" maxLength="2" maxOccurs="1" minLength="0" minOccurs="0" name="OPTION" useNamespace="-1" validateData="true"><DataFormat><ProfileCharacterFormat/></DataFormat></XMLElement><XMLElement comments="オブジェクトの個別ステータス (簡略形式)" dataType="character" isMappable="true" isNode="true" key="169" maxLength="4" maxOccurs="1" minLength="0" minOccurs="0" name="LOW" useNamespace="-1" validateData="true"><DataFormat><ProfileCharacterFormat/></DataFormat></XMLElement><XMLElement comments="オブジェクトの個別ステータス (簡略形式)" dataType="character" isMappable="true" isNode="true" key="170" maxLength="4" maxOccurs="1" minLength="0" minOccurs="0" name="HIGH" useNamespace="-1" validateData="true"><DataFormat><ProfileCharacterFormat/></DataFormat></XMLElement></XMLElement></Type><Type anonymous="false" declarationClass="cType" typeKey="172"><XMLElement comments="リターンパラメータ" dataType="character" isMappable="true" isNode="true" key="173" loopingOption="unique" maxOccurs="1" minOccurs="0" name="BAPIRET2" typeExpanded="false" typeKey="172" typeName="BAPIRET2" useNamespace="-1" validateData="false"><DataFormat><ProfileCharacterFormat/></DataFormat><XMLElement comments="メッセージType: S 正常、E エラー、W 警告、I 通知、A 強制終了" dataType="character" isMappable="true" isNode="true" key="174" maxLength="1" maxOccurs="1" minLength="0" minOccurs="0" name="TYPE" useNamespace="-1" validateData="true"><DataFormat><ProfileCharacterFormat/></DataFormat></XMLElement><XMLElement comments="メッセージクラス" dataType="character" isMappable="true" isNode="true" key="175" maxLength="20" maxOccurs="1" minLength="0" minOccurs="0" name="ID" useNamespace="-1" validateData="true"><DataFormat><ProfileCharacterFormat/></DataFormat></XMLElement><XMLElement comments="メッセージ番号" dataType="number" isMappable="true" isNode="true" key="176" maxOccurs="1" minOccurs="0" name="NUMBER" useNamespace="-1"><DataFormat><ProfileNumberFormat numberFormat=""/></DataFormat></XMLElement><XMLElement comments="メッセージテキスト" dataType="character" isMappable="true" isNode="true" key="177" maxLength="220" maxOccurs="1" minLength="0" minOccurs="0" name="MESSAGE" useNamespace="-1" validateData="true"><DataFormat><ProfileCharacterFormat/></DataFormat></XMLElement><XMLElement comments="アプリケーションログ: ログ番号" dataType="character" isMappable="true" isNode="true" key="178" maxLength="20" maxOccurs="1" minLength="0" minOccurs="0" name="LOG_NO" useNamespace="-1" validateData="true"><DataFormat><ProfileCharacterFormat/></DataFormat></XMLElement><XMLElement comments="アプリケーションログ: メッセージシリアル番号" dataType="number" isMappable="true" isNode="true" key="179" maxOccurs="1" minOccurs="0" name="LOG_MSG_NO" useNamespace="-1"><DataFormat><ProfileNumberFormat numberFormat=""/></DataFormat></XMLElement><XMLElement comments="メッセージ変数" dataType="character" isMappable="true" isNode="true" key="180" maxLength="50" maxOccurs="1" minLength="0" minOccurs="0" name="MESSAGE_V1" useNamespace="-1" validateData="true"><DataFormat><ProfileCharacterFormat/></DataFormat></XMLElement><XMLElement comments="メッセージ変数" dataType="character" isMappable="true" isNode="true" key="181" maxLength="50" maxOccurs="1" minLength="0" minOccurs="0" name="MESSAGE_V2" useNamespace="-1" validateData="true"><DataFormat><ProfileCharacterFormat/></DataFormat></XMLElement><XMLElement comments="メッセージ変数" dataType="character" isMappable="true" isNode="true" key="182" maxLength="50" maxOccurs="1" minLength="0" minOccurs="0" name="MESSAGE_V3" useNamespace="-1" validateData="true"><DataFormat><ProfileCharacterFormat/></DataFormat></XMLElement><XMLElement comments="メッセージ変数" dataType="character" isMappable="true" isNode="true" key="183" maxLength="50" maxOccurs="1" minLength="0" minOccurs="0" name="MESSAGE_V4" useNamespace="-1" validateData="true"><DataFormat><ProfileCharacterFormat/></DataFormat></XMLElement><XMLElement comments="パラメータ名" dataType="character" isMappable="true" isNode="true" key="184" maxLength="32" maxOccurs="1" minLength="0" minOccurs="0" name="PARAMETER" useNamespace="-1" validateData="true"><DataFormat><ProfileCharacterFormat/></DataFormat></XMLElement><XMLElement comments="パラメータの行" dataType="number" isMappable="true" isNode="true" key="185" maxOccurs="1" minOccurs="0" name="ROW" useNamespace="-1"><DataFormat><ProfileNumberFormat numberFormat=""/></DataFormat></XMLElement><XMLElement comments="パラメータの項目" dataType="character" isMappable="true" isNode="true" key="186" maxLength="30" maxOccurs="1" minLength="0" minOccurs="0" name="FIELD" useNamespace="-1" validateData="true"><DataFormat><ProfileCharacterFormat/></DataFormat></XMLElement><XMLElement comments="メッセージが発行された論理システム" dataType="character" isMappable="true" isNode="true" key="187" maxLength="10" maxOccurs="1" minLength="0" minOccurs="0" name="SYSTEM" useNamespace="-1" validateData="true"><DataFormat><ProfileCharacterFormat/></DataFormat></XMLElement></XMLElement></Type><Type anonymous="true" declarationClass="cType" typeKey="-65"><XMLElement comments="BAPI 通信構造: テキストの範囲" dataType="character" isMappable="true" isNode="true" key="66" loopingOption="unique" maxOccurs="1" minOccurs="0" name="DESCRIPT_RA" typeExpanded="false" typeKey="-65" useNamespace="-1" validateData="false"><DataFormat><ProfileCharacterFormat/></DataFormat><XMLElement dataType="character" isMappable="true" isNode="true" key="67" maxOccurs="-1" minOccurs="0" name="item" typeExpanded="false" typeKey="68" typeName="BAPI_ITOB_SEL_DESCRIPT" useNamespace="-1"><DataFormat><ProfileCharacterFormat/></DataFormat></XMLElement></XMLElement></Type><Type anonymous="true" declarationClass="cType" typeKey="-75"><XMLElement comments="BAPI 通信構造: 選択結果一覧" dataType="character" isMappable="true" isNode="true" key="76" loopingOption="unique" maxOccurs="1" minOccurs="1" name="FUNCLOC_LIST" typeExpanded="false" typeKey="-75" useNamespace="-1" validateData="false"><DataFormat><ProfileCharacterFormat/></DataFormat><XMLElement dataType="character" isMappable="true" isNode="true" key="77" maxOccurs="-1" minOccurs="0" name="item" typeExpanded="false" typeKey="78" typeName="BAPI_ITOB_FL_SEL_RESULT" useNamespace="-1"><DataFormat><ProfileCharacterFormat/></DataFormat></XMLElement></XMLElement></Type><Type anonymous="true" declarationClass="cType" typeKey="-92"><XMLElement comments="BAPI 通信構造: 機能場所の範囲" dataType="character" isMappable="true" isNode="true" key="93" loopingOption="unique" maxOccurs="1" minOccurs="0" name="FUNCLOC_RA" typeExpanded="false" typeKey="-92" useNamespace="-1" validateData="false"><DataFormat><ProfileCharacterFormat/></DataFormat><XMLElement dataType="character" isMappable="true" isNode="true" key="94" maxOccurs="-1" minOccurs="0" name="item" typeExpanded="false" typeKey="95" typeName="BAPI_ITOB_SEL_FUNCLOC" useNamespace="-1"><DataFormat><ProfileCharacterFormat/></DataFormat></XMLElement></XMLElement></Type><Type anonymous="true" declarationClass="cType" typeKey="-102"><XMLElement comments="BAPI 通信構造: 保全プラントの範囲" dataType="character" isMappable="true" isNode="true" key="103" loopingOption="unique" maxOccurs="1" minOccurs="0" name="MAINTPLANT_RA" typeExpanded="false" typeKey="-102" useNamespace="-1" validateData="false"><DataFormat><ProfileCharacterFormat/></DataFormat><XMLElement dataType="character" isMappable="true" isNode="true" key="104" maxOccurs="-1" minOccurs="0" name="item" typeExpanded="false" typeKey="105" typeName="BAPI_ITOB_SEL_MAINTPLANT" useNamespace="-1"><DataFormat><ProfileCharacterFormat/></DataFormat></XMLElement></XMLElement></Type><Type anonymous="true" declarationClass="cType" typeKey="-112"><XMLElement comments="BAPI Communication Structure: Range for Object Type" dataType="character" isMappable="true" isNode="true" key="113" loopingOption="unique" maxOccurs="1" minOccurs="0" name="OBJECTTYPE_RA" typeExpanded="false" typeKey="-112" useNamespace="-1" validateData="false"><DataFormat><ProfileCharacterFormat/></DataFormat><XMLElement dataType="character" isMappable="true" isNode="true" key="114" maxOccurs="-1" minOccurs="0" name="item" typeExpanded="false" typeKey="115" typeName="BAPI_ITOB_SEL_OBJECTTYPE" useNamespace="-1"><DataFormat><ProfileCharacterFormat/></DataFormat></XMLElement></XMLElement></Type><Type anonymous="true" declarationClass="cType" typeKey="-122"><XMLElement comments="BAPI Communication Structure: Range for Partner" dataType="character" isMappable="true" isNode="true" key="123" loopingOption="unique" maxOccurs="1" minOccurs="0" name="PARTNER_RA" typeExpanded="false" typeKey="-122" useNamespace="-1" validateData="false"><DataFormat><ProfileCharacterFormat/></DataFormat><XMLElement dataType="character" isMappable="true" isNode="true" key="124" maxOccurs="-1" minOccurs="0" name="item" typeExpanded="false" typeKey="125" typeName="BAPI_ITOB_SEL_PARTNER" useNamespace="-1"><DataFormat><ProfileCharacterFormat/></DataFormat></XMLElement></XMLElement></Type><Type anonymous="true" declarationClass="cType" typeKey="-132"><XMLElement comments="BAPI 通信構造: 保全計画グループの範囲" dataType="character" isMappable="true" isNode="true" key="133" loopingOption="unique" maxOccurs="1" minOccurs="0" name="PLANGROUP_RA" typeExpanded="false" typeKey="-132" useNamespace="-1" validateData="false"><DataFormat><ProfileCharacterFormat/></DataFormat><XMLElement dataType="character" isMappable="true" isNode="true" key="134" maxOccurs="-1" minOccurs="0" name="item" typeExpanded="false" typeKey="135" typeName="BAPI_ITOB_SEL_PLANGROUP" useNamespace="-1"><DataFormat><ProfileCharacterFormat/></DataFormat></XMLElement></XMLElement></Type><Type anonymous="true" declarationClass="cType" typeKey="-142"><XMLElement comments="BAPI 通信構造: 保全計画の範囲" dataType="character" isMappable="true" isNode="true" key="143" loopingOption="unique" maxOccurs="1" minOccurs="0" name="PLANPLANT_RA" typeExpanded="false" typeKey="-142" useNamespace="-1" validateData="false"><DataFormat><ProfileCharacterFormat/></DataFormat><XMLElement dataType="character" isMappable="true" isNode="true" key="144" maxOccurs="-1" minOccurs="0" name="item" typeExpanded="false" typeKey="145" typeName="BAPI_ITOB_SEL_PLANPLANT" useNamespace="-1"><DataFormat><ProfileCharacterFormat/></DataFormat></XMLElement></XMLElement></Type><Type anonymous="true" declarationClass="cType" typeKey="-152"><XMLElement comments="BAPI 通信構造: ソート項目の範囲" dataType="character" isMappable="true" isNode="true" key="153" loopingOption="unique" maxOccurs="1" minOccurs="0" name="SORTFIELD_RA" typeExpanded="false" typeKey="-152" useNamespace="-1" validateData="false"><DataFormat><ProfileCharacterFormat/></DataFormat><XMLElement dataType="character" isMappable="true" isNode="true" key="154" maxOccurs="-1" minOccurs="0" name="item" typeExpanded="false" typeKey="155" typeName="BAPI_ITOB_SEL_SORTFIELD" useNamespace="-1"><DataFormat><ProfileCharacterFormat/></DataFormat></XMLElement></XMLElement></Type><Type anonymous="true" declarationClass="cType" typeKey="-162"><XMLElement comments="BAPI Communication Structure: Range for Status" dataType="character" isMappable="true" isNode="true" key="163" loopingOption="unique" maxOccurs="1" minOccurs="0" name="STATUS_RA" typeExpanded="false" typeKey="-162" useNamespace="-1" validateData="false"><DataFormat><ProfileCharacterFormat/></DataFormat><XMLElement dataType="character" isMappable="true" isNode="true" key="164" maxOccurs="-1" minOccurs="0" name="item" typeExpanded="false" typeKey="165" typeName="BAPI_ITOB_SEL_STATUS" useNamespace="-1"><DataFormat><ProfileCharacterFormat/></DataFormat></XMLElement></XMLElement></Type></Types></XMLNamespace></Namespaces></XMLProfile></bns:object></bns:Component>