<?xml version="1.0" encoding="UTF-8" standalone="yes"?><bns:Component xmlns:xsi="http://www.w3.org/2001/XMLSchema-instance" xmlns:bns="http://api.platform.boomi.com/" folderFullPath="JERA Co., Inc./POC/JP1" componentId="3b7d68d6-df1f-46e2-b4dc-5b29ad019465" version="1" name="BAPI_XBP_JOB_START_IMMEDIATELY_request" type="profile.xml" createdDate="2020-02-28T06:42:54Z" createdBy="walid.bargaoui@avaxia-group.com" modifiedDate="2020-02-28T06:42:54Z" modifiedBy="walid.bargaoui@avaxia-group.com" deleted="false" currentVersion="true" folderName="JP1" folderId="RjozMTI1MTQy" branchName="main" branchId="QjozMzg0ODI"><bns:encryptedValues/><bns:object><XMLProfile xmlns="" modelVersion="2" strict="true"><ProfileProperties><XMLGeneralInfo/><XMLOptions encoding="utf8" implicitElementOrdering="true" parseRespectMaxOccurs="true"/></ProfileProperties><DataElements><XMLElement dataType="character" isMappable="true" isNode="true" key="1" maxOccurs="1" minOccurs="1" name="BAPI_XBP_JOB_START_IMMEDIATELY" typeExpanded="false" typeKey="-1" useNamespace="-1"><DataFormat><ProfileCharacterFormat/></DataFormat><XMLElement comments="Name of the SAP-External User" dataType="character" isMappable="true" isNode="true" key="10" loopingOption="unique" maxLength="16" maxOccurs="1" minLength="0" minOccurs="1" name="EXTERNAL_USER_NAME" typeKey="-1" useNamespace="-1" validateData="true"><DataFormat><ProfileCharacterFormat/></DataFormat></XMLElement><XMLElement comments="Job Count" dataType="character" isMappable="true" isNode="true" key="12" loopingOption="unique" maxLength="8" maxOccurs="1" minLength="0" minOccurs="1" name="JOBCOUNT" typeKey="-1" useNamespace="-1" validateData="true"><DataFormat><ProfileCharacterFormat/></DataFormat></XMLElement><XMLElement comments="Job Name" dataType="character" isMappable="true" isNode="true" key="14" loopingOption="unique" maxLength="32" maxOccurs="1" minLength="0" minOccurs="1" name="JOBNAME" typeKey="-1" useNamespace="-1" validateData="true"><DataFormat><ProfileCharacterFormat/></DataFormat></XMLElement><XMLElement comments="Server Group Name Background Processing" dataType="character" isMappable="true" isNode="true" key="16" loopingOption="unique" maxLength="20" maxOccurs="1" minLength="0" minOccurs="0" name="TARGET_GROUP" typeKey="-1" useNamespace="-1" validateData="true"><DataFormat><ProfileCharacterFormat/></DataFormat></XMLElement><XMLElement comments="Target Application Server for the Job" dataType="character" isMappable="true" isNode="true" key="18" loopingOption="unique" maxLength="20" maxOccurs="1" minLength="0" minOccurs="1" name="TARGET_SERVER" typeKey="-1" useNamespace="-1" validateData="true"><DataFormat><ProfileCharacterFormat/></DataFormat></XMLElement></XMLElement></DataElements><Namespaces><XMLNamespace key="-1" name="Empty Namespace" prefix="ns1"><Types><Type anonymous="true" declarationClass="cType" typeKey="-2"><XMLElement dataType="character" isMappable="true" isNode="true" key="3" loopingOption="unique" maxOccurs="1" minOccurs="0" name="BAPI_XBP_JOB_START_IMMEDIATELY" typeExpanded="false" typeKey="-2" useNamespace="-1" validateData="false"><DataFormat><ProfileCharacterFormat/></DataFormat><XMLElement comments="Name of the SAP-External User" dataType="character" isMappable="true" isNode="true" key="4" maxLength="16" maxOccurs="1" minLength="0" minOccurs="1" name="EXTERNAL_USER_NAME" useNamespace="-1" validateData="true"><DataFormat><ProfileCharacterFormat/></DataFormat></XMLElement><XMLElement comments="Job Count" dataType="character" isMappable="true" isNode="true" key="5" maxLength="8" maxOccurs="1" minLength="0" minOccurs="1" name="JOBCOUNT" useNamespace="-1" validateData="true"><DataFormat><ProfileCharacterFormat/></DataFormat></XMLElement><XMLElement comments="Job Name" dataType="character" isMappable="true" isNode="true" key="6" maxLength="32" maxOccurs="1" minLength="0" minOccurs="1" name="JOBNAME" useNamespace="-1" validateData="true"><DataFormat><ProfileCharacterFormat/></DataFormat></XMLElement><XMLElement comments="Server Group Name Background Processing" dataType="character" isMappable="true" isNode="true" key="7" maxLength="20" maxOccurs="1" minLength="0" minOccurs="0" name="TARGET_GROUP" useNamespace="-1" validateData="true"><DataFormat><ProfileCharacterFormat/></DataFormat></XMLElement><XMLElement comments="Target Application Server for the Job" dataType="character" isMappable="true" isNode="true" key="8" maxLength="20" maxOccurs="1" minLength="0" minOccurs="1" name="TARGET_SERVER" useNamespace="-1" validateData="true"><DataFormat><ProfileCharacterFormat/></DataFormat></XMLElement></XMLElement></Type></Types></XMLNamespace></Namespaces></XMLProfile></bns:object></bns:Component>