<?xml version="1.0" encoding="UTF-8" standalone="yes"?><bns:Component xmlns:xsi="http://www.w3.org/2001/XMLSchema-instance" xmlns:bns="http://api.platform.boomi.com/" folderFullPath="JERA Co., Inc./New_HR_SFSF/Company_SFSF" componentId="a75a0bfd-679e-4a0f-acaf-97b11f05c25c" version="1" name="SuccessFactors — Partner Connector SFOData.PerAddressDEFLT EXECUTE Request" type="profile.xml" createdDate="2022-08-30T07:18:06Z" createdBy="Daly.Fadhloun@avaxia-group.com" modifiedDate="2022-08-30T07:18:06Z" modifiedBy="Daly.Fadhloun@avaxia-group.com" deleted="false" currentVersion="true" folderName="Company_SFSF" folderId="Rjo0OTk1Nzcz" branchName="main" branchId="QjozMzg0ODI"><bns:encryptedValues/><bns:object><XMLProfile xmlns="" modelVersion="2" strict="true"><ProfileProperties><XMLGeneralInfo/><XMLOptions encoding="utf8" implicitElementOrdering="true" parseRespectMaxOccurs="true" respectMinOccurs="true"/></ProfileProperties><DataElements><XMLElement dataType="character" isMappable="true" isNode="true" key="1" maxOccurs="1" minOccurs="1" name="SFOData.PerAddressDEFLT" typeExpanded="false" typeKey="-1" useNamespace="-1"><DataFormat><ProfileCharacterFormat/></DataFormat><XMLElement comments="Address Type" dataType="character" isMappable="true" isNode="true" key="58" loopingOption="unique" maxLength="30" maxOccurs="1" minOccurs="0" name="addressType" typeKey="-1" useNamespace="-1" validateData="true"><DataFormat><ProfileCharacterFormat/></DataFormat></XMLElement><XMLElement comments="Person ID External" dataType="character" isMappable="true" isNode="true" key="60" loopingOption="unique" maxLength="100" maxOccurs="1" minOccurs="0" name="personIdExternal" typeKey="-1" useNamespace="-1" validateData="true"><DataFormat><ProfileCharacterFormat/></DataFormat></XMLElement><XMLElement comments="Start Date" dataType="datetime" isMappable="true" isNode="true" key="62" loopingOption="unique" maxOccurs="1" minOccurs="0" name="startDate" typeKey="-1" useNamespace="-1" validateData="false"><DataFormat><ProfileDateFormat dateFormat="yyyy-MM-dd"/></DataFormat></XMLElement><XMLElement comments="Set these elements to change the primary business key." dataType="character" isMappable="true" isNode="true" key="64" loopingOption="unique" maxOccurs="1" minOccurs="0" name="__UpdatedBusinessKey" typeExpanded="false" typeKey="-1" useNamespace="-1" validateData="false"><DataFormat><ProfileCharacterFormat/></DataFormat><XMLElement comments="Address Type" dataType="character" isMappable="true" isNode="true" key="154" loopingOption="unique" maxLength="30" maxOccurs="1" minOccurs="0" name="addressType" typeKey="-1" useNamespace="-1" validateData="true"><DataFormat><ProfileCharacterFormat/></DataFormat></XMLElement><XMLElement comments="Person ID External" dataType="character" isMappable="true" isNode="true" key="156" loopingOption="unique" maxLength="100" maxOccurs="1" minOccurs="0" name="personIdExternal" typeKey="-1" useNamespace="-1" validateData="true"><DataFormat><ProfileCharacterFormat/></DataFormat></XMLElement><XMLElement comments="Start Date" dataType="datetime" isMappable="true" isNode="true" key="158" loopingOption="unique" maxOccurs="1" minOccurs="0" name="startDate" typeKey="-1" useNamespace="-1" validateData="false"><DataFormat><ProfileDateFormat dateFormat="yyyy-MM-dd"/></DataFormat></XMLElement></XMLElement><XMLElement comments="City" dataType="character" isMappable="true" isNode="true" key="66" loopingOption="unique" maxLength="256" maxOccurs="1" minOccurs="0" name="address1" typeKey="-1" useNamespace="-1" validateData="true"><DataFormat><ProfileCharacterFormat/></DataFormat></XMLElement><XMLElement comments="Apartment" dataType="character" isMappable="true" isNode="true" key="68" loopingOption="unique" maxLength="256" maxOccurs="1" minOccurs="0" name="address10" typeKey="-1" useNamespace="-1" validateData="true"><DataFormat><ProfileCharacterFormat/></DataFormat></XMLElement><XMLElement comments="Structure Status" dataType="character" isMappable="true" isNode="true" key="70" loopingOption="unique" maxLength="256" maxOccurs="1" minOccurs="0" name="address11" typeKey="-1" useNamespace="-1" validateData="true"><DataFormat><ProfileCharacterFormat/></DataFormat></XMLElement><XMLElement comments="City" dataType="character" isMappable="true" isNode="true" key="72" loopingOption="unique" maxLength="256" maxOccurs="1" minOccurs="0" name="address12" typeKey="-1" useNamespace="-1" validateData="true"><DataFormat><ProfileCharacterFormat/></DataFormat></XMLElement><XMLElement comments="Street Number" dataType="character" isMappable="true" isNode="true" key="74" loopingOption="unique" maxLength="256" maxOccurs="1" minOccurs="0" name="address13" typeKey="-1" useNamespace="-1" validateData="true"><DataFormat><ProfileCharacterFormat/></DataFormat></XMLElement><XMLElement comments="City District Type" dataType="character" isMappable="true" isNode="true" key="76" loopingOption="unique" maxLength="256" maxOccurs="1" minOccurs="0" name="address14" typeKey="-1" useNamespace="-1" validateData="true"><DataFormat><ProfileCharacterFormat/></DataFormat></XMLElement><XMLElement comments="Plan Structure" dataType="character" isMappable="true" isNode="true" key="78" loopingOption="unique" maxLength="256" maxOccurs="1" minOccurs="0" name="address15" typeKey="-1" useNamespace="-1" validateData="true"><DataFormat><ProfileCharacterFormat/></DataFormat></XMLElement><XMLElement comments="Plan Structure Type" dataType="character" isMappable="true" isNode="true" key="80" loopingOption="unique" maxLength="256" maxOccurs="1" minOccurs="0" name="address16" typeKey="-1" useNamespace="-1" validateData="true"><DataFormat><ProfileCharacterFormat/></DataFormat></XMLElement><XMLElement comments="County Type" dataType="character" isMappable="true" isNode="true" key="82" loopingOption="unique" maxLength="256" maxOccurs="1" minOccurs="0" name="address17" typeKey="-1" useNamespace="-1" validateData="true"><DataFormat><ProfileCharacterFormat/></DataFormat></XMLElement><XMLElement comments="Region Type" dataType="character" isMappable="true" isNode="true" key="84" loopingOption="unique" maxLength="256" maxOccurs="1" minOccurs="0" name="address18" typeKey="-1" useNamespace="-1" validateData="true"><DataFormat><ProfileCharacterFormat/></DataFormat></XMLElement><XMLElement comments="District" dataType="character" isMappable="true" isNode="true" key="86" loopingOption="unique" maxLength="256" maxOccurs="1" minOccurs="0" name="address2" typeKey="-1" useNamespace="-1" validateData="true"><DataFormat><ProfileCharacterFormat/></DataFormat></XMLElement><XMLElement comments="Care Of" dataType="character" isMappable="true" isNode="true" key="88" loopingOption="unique" maxLength="40" maxOccurs="1" minOccurs="0" name="address20" typeKey="-1" useNamespace="-1" validateData="true"><DataFormat><ProfileCharacterFormat/></DataFormat></XMLElement><XMLElement comments="Municipality" dataType="character" isMappable="true" isNode="true" key="90" loopingOption="unique" maxLength="256" maxOccurs="1" minOccurs="0" name="address3" typeKey="-1" useNamespace="-1" validateData="true"><DataFormat><ProfileCharacterFormat/></DataFormat></XMLElement><XMLElement comments="Parish Name" dataType="character" isMappable="true" isNode="true" key="92" loopingOption="unique" maxLength="256" maxOccurs="1" minOccurs="0" name="address4" typeKey="-1" useNamespace="-1" validateData="true"><DataFormat><ProfileCharacterFormat/></DataFormat></XMLElement><XMLElement comments="Town" dataType="character" isMappable="true" isNode="true" key="94" loopingOption="unique" maxLength="256" maxOccurs="1" minOccurs="0" name="address5" typeKey="-1" useNamespace="-1" validateData="true"><DataFormat><ProfileCharacterFormat/></DataFormat></XMLElement><XMLElement comments="Municipality" dataType="character" isMappable="true" isNode="true" key="96" loopingOption="unique" maxLength="256" maxOccurs="1" minOccurs="0" name="address6" typeKey="-1" useNamespace="-1" validateData="true"><DataFormat><ProfileCharacterFormat/></DataFormat></XMLElement><XMLElement comments="Camp" dataType="character" isMappable="true" isNode="true" key="98" loopingOption="unique" maxLength="256" maxOccurs="1" minOccurs="0" name="address7" typeKey="-1" useNamespace="-1" validateData="true"><DataFormat><ProfileCharacterFormat/></DataFormat></XMLElement><XMLElement comments="Camp" dataType="character" isMappable="true" isNode="true" key="100" loopingOption="unique" maxLength="256" maxOccurs="1" minOccurs="0" name="address8" typeKey="-1" useNamespace="-1" validateData="true"><DataFormat><ProfileCharacterFormat/></DataFormat></XMLElement><XMLElement comments="Street Type" dataType="character" isMappable="true" isNode="true" key="102" loopingOption="unique" maxLength="256" maxOccurs="1" minOccurs="0" name="address9" typeKey="-1" useNamespace="-1" validateData="true"><DataFormat><ProfileCharacterFormat/></DataFormat></XMLElement><XMLElement comments="District" dataType="character" isMappable="true" isNode="true" key="104" loopingOption="unique" maxLength="256" maxOccurs="1" minOccurs="0" name="city" typeKey="-1" useNamespace="-1" validateData="true"><DataFormat><ProfileCharacterFormat/></DataFormat></XMLElement><XMLElement comments="Country" dataType="character" isMappable="true" isNode="true" key="106" loopingOption="unique" maxLength="256" maxOccurs="1" minOccurs="0" name="country" typeKey="-1" useNamespace="-1" validateData="true"><DataFormat><ProfileCharacterFormat/></DataFormat></XMLElement><XMLElement comments="District" dataType="character" isMappable="true" isNode="true" key="108" loopingOption="unique" maxLength="256" maxOccurs="1" minOccurs="0" name="county" typeKey="-1" useNamespace="-1" validateData="true"><DataFormat><ProfileCharacterFormat/></DataFormat></XMLElement><XMLElement comments="Created By" dataType="character" isMappable="true" isNode="true" key="110" loopingOption="unique" maxLength="100" maxOccurs="1" minOccurs="0" name="createdBy" typeKey="-1" useNamespace="-1" validateData="true"><DataFormat><ProfileCharacterFormat/></DataFormat></XMLElement><XMLElement comments="Created Date Time" dataType="datetime" isMappable="true" isNode="true" key="112" loopingOption="unique" maxOccurs="1" minOccurs="0" name="createdDateTime" typeKey="-1" useNamespace="-1" validateData="false"><DataFormat><ProfileDateFormat dateFormat="yyyy-MM-dd'T'HH:mm:ss.SSSZZ"/></DataFormat></XMLElement><XMLElement comments="Created On" dataType="datetime" isMappable="true" isNode="true" key="114" loopingOption="unique" maxOccurs="1" minOccurs="0" name="createdOn" typeKey="-1" useNamespace="-1" validateData="false"><DataFormat><ProfileDateFormat dateFormat="yyyy-MM-dd'T'HH:mm:ss.SSSZZ"/></DataFormat></XMLElement><XMLElement comments="Communication type" dataType="character" isMappable="true" isNode="true" key="116" loopingOption="unique" maxLength="256" maxOccurs="1" minOccurs="0" name="customString1" typeKey="-1" useNamespace="-1" validateData="true"><DataFormat><ProfileCharacterFormat/></DataFormat></XMLElement><XMLElement comments="Relationship Type" dataType="character" isMappable="true" isNode="true" key="118" loopingOption="unique" maxLength="30" maxOccurs="1" minOccurs="0" name="customString10" typeKey="-1" useNamespace="-1" validateData="true"><DataFormat><ProfileCharacterFormat/></DataFormat></XMLElement><XMLElement comments="Phone Number" dataType="character" isMappable="true" isNode="true" key="120" loopingOption="unique" maxLength="256" maxOccurs="1" minOccurs="0" name="customString2" typeKey="-1" useNamespace="-1" validateData="true"><DataFormat><ProfileCharacterFormat/></DataFormat></XMLElement><XMLElement comments="Unaccompanied Posting" dataType="character" isMappable="true" isNode="true" key="122" loopingOption="unique" maxLength="256" maxOccurs="1" minOccurs="0" name="customString4" typeKey="-1" useNamespace="-1" validateData="true"><DataFormat><ProfileCharacterFormat/></DataFormat></XMLElement><XMLElement comments="Housing Classification" dataType="character" isMappable="true" isNode="true" key="124" loopingOption="unique" maxLength="256" maxOccurs="1" minOccurs="0" name="customString5" typeKey="-1" useNamespace="-1" validateData="true"><DataFormat><ProfileCharacterFormat/></DataFormat></XMLElement><XMLElement comments="Municipal city code" dataType="character" isMappable="true" isNode="true" key="126" loopingOption="unique" maxLength="256" maxOccurs="1" minOccurs="0" name="customString6" typeKey="-1" useNamespace="-1" validateData="true"><DataFormat><ProfileCharacterFormat/></DataFormat></XMLElement><XMLElement comments="Owned House" dataType="character" isMappable="true" isNode="true" key="128" loopingOption="unique" maxLength="256" maxOccurs="1" minOccurs="0" name="customString7" typeKey="-1" useNamespace="-1" validateData="true"><DataFormat><ProfileCharacterFormat/></DataFormat></XMLElement><XMLElement comments="Foreign Country of Residence" dataType="character" isMappable="true" isNode="true" key="130" loopingOption="unique" maxLength="256" maxOccurs="1" minOccurs="0" name="customString8" typeKey="-1" useNamespace="-1" validateData="true"><DataFormat><ProfileCharacterFormat/></DataFormat></XMLElement><XMLElement comments="Head of Household" dataType="character" isMappable="true" isNode="true" key="132" loopingOption="unique" maxLength="256" maxOccurs="1" minOccurs="0" name="customString9" typeKey="-1" useNamespace="-1" validateData="true"><DataFormat><ProfileCharacterFormat/></DataFormat></XMLElement><XMLElement comments="End Date" dataType="datetime" isMappable="true" isNode="true" key="134" loopingOption="unique" maxOccurs="1" minOccurs="0" name="endDate" typeKey="-1" useNamespace="-1" validateData="false"><DataFormat><ProfileDateFormat dateFormat="yyyy-MM-dd"/></DataFormat></XMLElement><XMLElement comments="Include All Records" dataType="character" isMappable="true" isNode="true" key="136" loopingOption="unique" maxOccurs="1" minOccurs="0" name="includeAllRecords" typeKey="-1" useNamespace="-1" validateData="false"><DataFormat><ProfileCharacterFormat/></DataFormat></XMLElement><XMLElement comments="Last Modified By" dataType="character" isMappable="true" isNode="true" key="138" loopingOption="unique" maxLength="100" maxOccurs="1" minOccurs="0" name="lastModifiedBy" typeKey="-1" useNamespace="-1" validateData="true"><DataFormat><ProfileCharacterFormat/></DataFormat></XMLElement><XMLElement comments="Last Modified Date Time" dataType="datetime" isMappable="true" isNode="true" key="140" loopingOption="unique" maxOccurs="1" minOccurs="0" name="lastModifiedDateTime" typeKey="-1" useNamespace="-1" validateData="false"><DataFormat><ProfileDateFormat dateFormat="yyyy-MM-dd'T'HH:mm:ss.SSSZZ"/></DataFormat></XMLElement><XMLElement comments="Last Modified On" dataType="datetime" isMappable="true" isNode="true" key="142" loopingOption="unique" maxOccurs="1" minOccurs="0" name="lastModifiedOn" typeKey="-1" useNamespace="-1" validateData="false"><DataFormat><ProfileDateFormat dateFormat="yyyy-MM-dd'T'HH:mm:ss.SSSZZ"/></DataFormat></XMLElement><XMLElement comments="notes" dataType="character" isMappable="true" isNode="true" key="144" loopingOption="unique" maxLength="4000" maxOccurs="1" minOccurs="0" name="notes" typeKey="-1" useNamespace="-1" validateData="true"><DataFormat><ProfileCharacterFormat/></DataFormat></XMLElement><XMLElement comments="operation" dataType="character" isMappable="true" isNode="true" key="146" loopingOption="unique" maxOccurs="1" minOccurs="0" name="operation" typeKey="-1" useNamespace="-1" validateData="false"><DataFormat><ProfileCharacterFormat/></DataFormat></XMLElement><XMLElement comments="Province" dataType="character" isMappable="true" isNode="true" key="148" loopingOption="unique" maxLength="256" maxOccurs="1" minOccurs="0" name="province" typeKey="-1" useNamespace="-1" validateData="true"><DataFormat><ProfileCharacterFormat/></DataFormat></XMLElement><XMLElement comments="State" dataType="character" isMappable="true" isNode="true" key="150" loopingOption="unique" maxLength="256" maxOccurs="1" minOccurs="0" name="state" typeKey="-1" useNamespace="-1" validateData="true"><DataFormat><ProfileCharacterFormat/></DataFormat></XMLElement><XMLElement comments="Postal Code" dataType="character" isMappable="true" isNode="true" key="152" loopingOption="unique" maxLength="256" maxOccurs="1" minOccurs="0" name="zipCode" typeKey="-1" useNamespace="-1" validateData="true"><DataFormat><ProfileCharacterFormat/></DataFormat></XMLElement></XMLElement></DataElements><Namespaces><XMLNamespace key="-1" name="Empty Namespace" prefix="ns1"><Types><Type anonymous="true" declarationClass="cType" typeKey="-8"><XMLElement comments="Set these elements to change the primary business key." dataType="character" isMappable="true" isNode="true" key="9" loopingOption="unique" maxOccurs="1" minOccurs="0" name="__UpdatedBusinessKey" typeExpanded="false" typeKey="-8" useNamespace="-1" validateData="false"><DataFormat><ProfileCharacterFormat/></DataFormat><XMLElement comments="Address Type" dataType="character" isMappable="true" isNode="true" key="10" maxLength="30" maxOccurs="1" minOccurs="0" name="addressType" useNamespace="-1" validateData="true"><DataFormat><ProfileCharacterFormat/></DataFormat></XMLElement><XMLElement comments="Person ID External" dataType="character" isMappable="true" isNode="true" key="11" maxLength="100" maxOccurs="1" minOccurs="0" name="personIdExternal" useNamespace="-1" validateData="true"><DataFormat><ProfileCharacterFormat/></DataFormat></XMLElement><XMLElement comments="Start Date" dataType="datetime" isMappable="true" isNode="true" key="12" maxOccurs="1" minOccurs="0" name="startDate" useNamespace="-1"><DataFormat><ProfileDateFormat dateFormat="yyyy-MM-dd"/></DataFormat></XMLElement></XMLElement></Type><Type anonymous="true" declarationClass="cType" typeKey="-2"><XMLElement dataType="character" isMappable="true" isNode="true" key="3" loopingOption="unique" maxOccurs="1" minOccurs="0" name="SFOData.PerAddressDEFLT" typeExpanded="false" typeKey="-2" useNamespace="-1" validateData="false"><DataFormat><ProfileCharacterFormat/></DataFormat><XMLElement comments="Address Type" dataType="character" isMappable="true" isNode="true" key="4" maxLength="30" maxOccurs="1" minOccurs="0" name="addressType" useNamespace="-1" validateData="true"><DataFormat><ProfileCharacterFormat/></DataFormat></XMLElement><XMLElement comments="Person ID External" dataType="character" isMappable="true" isNode="true" key="5" maxLength="100" maxOccurs="1" minOccurs="0" name="personIdExternal" useNamespace="-1" validateData="true"><DataFormat><ProfileCharacterFormat/></DataFormat></XMLElement><XMLElement comments="Start Date" dataType="datetime" isMappable="true" isNode="true" key="6" maxOccurs="1" minOccurs="0" name="startDate" useNamespace="-1"><DataFormat><ProfileDateFormat dateFormat="yyyy-MM-dd"/></DataFormat></XMLElement><XMLElement comments="Set these elements to change the primary business key." dataType="character" isMappable="true" isNode="true" key="7" maxOccurs="1" minOccurs="0" name="__UpdatedBusinessKey" typeExpanded="false" typeKey="-8" useNamespace="-1"><DataFormat><ProfileCharacterFormat/></DataFormat></XMLElement><XMLElement comments="City" dataType="character" isMappable="true" isNode="true" key="13" maxLength="256" maxOccurs="1" minOccurs="0" name="address1" useNamespace="-1" validateData="true"><DataFormat><ProfileCharacterFormat/></DataFormat></XMLElement><XMLElement comments="Apartment" dataType="character" isMappable="true" isNode="true" key="14" maxLength="256" maxOccurs="1" minOccurs="0" name="address10" useNamespace="-1" validateData="true"><DataFormat><ProfileCharacterFormat/></DataFormat></XMLElement><XMLElement comments="Structure Status" dataType="character" isMappable="true" isNode="true" key="15" maxLength="256" maxOccurs="1" minOccurs="0" name="address11" useNamespace="-1" validateData="true"><DataFormat><ProfileCharacterFormat/></DataFormat></XMLElement><XMLElement comments="City" dataType="character" isMappable="true" isNode="true" key="16" maxLength="256" maxOccurs="1" minOccurs="0" name="address12" useNamespace="-1" validateData="true"><DataFormat><ProfileCharacterFormat/></DataFormat></XMLElement><XMLElement comments="Street Number" dataType="character" isMappable="true" isNode="true" key="17" maxLength="256" maxOccurs="1" minOccurs="0" name="address13" useNamespace="-1" validateData="true"><DataFormat><ProfileCharacterFormat/></DataFormat></XMLElement><XMLElement comments="City District Type" dataType="character" isMappable="true" isNode="true" key="18" maxLength="256" maxOccurs="1" minOccurs="0" name="address14" useNamespace="-1" validateData="true"><DataFormat><ProfileCharacterFormat/></DataFormat></XMLElement><XMLElement comments="Plan Structure" dataType="character" isMappable="true" isNode="true" key="19" maxLength="256" maxOccurs="1" minOccurs="0" name="address15" useNamespace="-1" validateData="true"><DataFormat><ProfileCharacterFormat/></DataFormat></XMLElement><XMLElement comments="Plan Structure Type" dataType="character" isMappable="true" isNode="true" key="20" maxLength="256" maxOccurs="1" minOccurs="0" name="address16" useNamespace="-1" validateData="true"><DataFormat><ProfileCharacterFormat/></DataFormat></XMLElement><XMLElement comments="County Type" dataType="character" isMappable="true" isNode="true" key="21" maxLength="256" maxOccurs="1" minOccurs="0" name="address17" useNamespace="-1" validateData="true"><DataFormat><ProfileCharacterFormat/></DataFormat></XMLElement><XMLElement comments="Region Type" dataType="character" isMappable="true" isNode="true" key="22" maxLength="256" maxOccurs="1" minOccurs="0" name="address18" useNamespace="-1" validateData="true"><DataFormat><ProfileCharacterFormat/></DataFormat></XMLElement><XMLElement comments="District" dataType="character" isMappable="true" isNode="true" key="23" maxLength="256" maxOccurs="1" minOccurs="0" name="address2" useNamespace="-1" validateData="true"><DataFormat><ProfileCharacterFormat/></DataFormat></XMLElement><XMLElement comments="Care Of" dataType="character" isMappable="true" isNode="true" key="24" maxLength="40" maxOccurs="1" minOccurs="0" name="address20" useNamespace="-1" validateData="true"><DataFormat><ProfileCharacterFormat/></DataFormat></XMLElement><XMLElement comments="Municipality" dataType="character" isMappable="true" isNode="true" key="25" maxLength="256" maxOccurs="1" minOccurs="0" name="address3" useNamespace="-1" validateData="true"><DataFormat><ProfileCharacterFormat/></DataFormat></XMLElement><XMLElement comments="Parish Name" dataType="character" isMappable="true" isNode="true" key="26" maxLength="256" maxOccurs="1" minOccurs="0" name="address4" useNamespace="-1" validateData="true"><DataFormat><ProfileCharacterFormat/></DataFormat></XMLElement><XMLElement comments="Town" dataType="character" isMappable="true" isNode="true" key="27" maxLength="256" maxOccurs="1" minOccurs="0" name="address5" useNamespace="-1" validateData="true"><DataFormat><ProfileCharacterFormat/></DataFormat></XMLElement><XMLElement comments="Municipality" dataType="character" isMappable="true" isNode="true" key="28" maxLength="256" maxOccurs="1" minOccurs="0" name="address6" useNamespace="-1" validateData="true"><DataFormat><ProfileCharacterFormat/></DataFormat></XMLElement><XMLElement comments="Camp" dataType="character" isMappable="true" isNode="true" key="29" maxLength="256" maxOccurs="1" minOccurs="0" name="address7" useNamespace="-1" validateData="true"><DataFormat><ProfileCharacterFormat/></DataFormat></XMLElement><XMLElement comments="Camp" dataType="character" isMappable="true" isNode="true" key="30" maxLength="256" maxOccurs="1" minOccurs="0" name="address8" useNamespace="-1" validateData="true"><DataFormat><ProfileCharacterFormat/></DataFormat></XMLElement><XMLElement comments="Street Type" dataType="character" isMappable="true" isNode="true" key="31" maxLength="256" maxOccurs="1" minOccurs="0" name="address9" useNamespace="-1" validateData="true"><DataFormat><ProfileCharacterFormat/></DataFormat></XMLElement><XMLElement comments="District" dataType="character" isMappable="true" isNode="true" key="32" maxLength="256" maxOccurs="1" minOccurs="0" name="city" useNamespace="-1" validateData="true"><DataFormat><ProfileCharacterFormat/></DataFormat></XMLElement><XMLElement comments="Country" dataType="character" isMappable="true" isNode="true" key="33" maxLength="256" maxOccurs="1" minOccurs="0" name="country" useNamespace="-1" validateData="true"><DataFormat><ProfileCharacterFormat/></DataFormat></XMLElement><XMLElement comments="District" dataType="character" isMappable="true" isNode="true" key="34" maxLength="256" maxOccurs="1" minOccurs="0" name="county" useNamespace="-1" validateData="true"><DataFormat><ProfileCharacterFormat/></DataFormat></XMLElement><XMLElement comments="Created By" dataType="character" isMappable="true" isNode="true" key="35" maxLength="100" maxOccurs="1" minOccurs="0" name="createdBy" useNamespace="-1" validateData="true"><DataFormat><ProfileCharacterFormat/></DataFormat></XMLElement><XMLElement comments="Created Date Time" dataType="datetime" isMappable="true" isNode="true" key="36" maxOccurs="1" minOccurs="0" name="createdDateTime" useNamespace="-1"><DataFormat><ProfileDateFormat dateFormat="yyyy-MM-dd'T'HH:mm:ss.SSSZZ"/></DataFormat></XMLElement><XMLElement comments="Created On" dataType="datetime" isMappable="true" isNode="true" key="37" maxOccurs="1" minOccurs="0" name="createdOn" useNamespace="-1"><DataFormat><ProfileDateFormat dateFormat="yyyy-MM-dd'T'HH:mm:ss.SSSZZ"/></DataFormat></XMLElement><XMLElement comments="Communication type" dataType="character" isMappable="true" isNode="true" key="38" maxLength="256" maxOccurs="1" minOccurs="0" name="customString1" useNamespace="-1" validateData="true"><DataFormat><ProfileCharacterFormat/></DataFormat></XMLElement><XMLElement comments="Relationship Type" dataType="character" isMappable="true" isNode="true" key="39" maxLength="30" maxOccurs="1" minOccurs="0" name="customString10" useNamespace="-1" validateData="true"><DataFormat><ProfileCharacterFormat/></DataFormat></XMLElement><XMLElement comments="Phone Number" dataType="character" isMappable="true" isNode="true" key="40" maxLength="256" maxOccurs="1" minOccurs="0" name="customString2" useNamespace="-1" validateData="true"><DataFormat><ProfileCharacterFormat/></DataFormat></XMLElement><XMLElement comments="Unaccompanied Posting" dataType="character" isMappable="true" isNode="true" key="41" maxLength="256" maxOccurs="1" minOccurs="0" name="customString4" useNamespace="-1" validateData="true"><DataFormat><ProfileCharacterFormat/></DataFormat></XMLElement><XMLElement comments="Housing Classification" dataType="character" isMappable="true" isNode="true" key="42" maxLength="256" maxOccurs="1" minOccurs="0" name="customString5" useNamespace="-1" validateData="true"><DataFormat><ProfileCharacterFormat/></DataFormat></XMLElement><XMLElement comments="Municipal city code" dataType="character" isMappable="true" isNode="true" key="43" maxLength="256" maxOccurs="1" minOccurs="0" name="customString6" useNamespace="-1" validateData="true"><DataFormat><ProfileCharacterFormat/></DataFormat></XMLElement><XMLElement comments="Owned House" dataType="character" isMappable="true" isNode="true" key="44" maxLength="256" maxOccurs="1" minOccurs="0" name="customString7" useNamespace="-1" validateData="true"><DataFormat><ProfileCharacterFormat/></DataFormat></XMLElement><XMLElement comments="Foreign Country of Residence" dataType="character" isMappable="true" isNode="true" key="45" maxLength="256" maxOccurs="1" minOccurs="0" name="customString8" useNamespace="-1" validateData="true"><DataFormat><ProfileCharacterFormat/></DataFormat></XMLElement><XMLElement comments="Head of Household" dataType="character" isMappable="true" isNode="true" key="46" maxLength="256" maxOccurs="1" minOccurs="0" name="customString9" useNamespace="-1" validateData="true"><DataFormat><ProfileCharacterFormat/></DataFormat></XMLElement><XMLElement comments="End Date" dataType="datetime" isMappable="true" isNode="true" key="47" maxOccurs="1" minOccurs="0" name="endDate" useNamespace="-1"><DataFormat><ProfileDateFormat dateFormat="yyyy-MM-dd"/></DataFormat></XMLElement><XMLElement comments="Include All Records" dataType="character" isMappable="true" isNode="true" key="48" maxOccurs="1" minOccurs="0" name="includeAllRecords" useNamespace="-1"><DataFormat><ProfileCharacterFormat/></DataFormat></XMLElement><XMLElement comments="Last Modified By" dataType="character" isMappable="true" isNode="true" key="49" maxLength="100" maxOccurs="1" minOccurs="0" name="lastModifiedBy" useNamespace="-1" validateData="true"><DataFormat><ProfileCharacterFormat/></DataFormat></XMLElement><XMLElement comments="Last Modified Date Time" dataType="datetime" isMappable="true" isNode="true" key="50" maxOccurs="1" minOccurs="0" name="lastModifiedDateTime" useNamespace="-1"><DataFormat><ProfileDateFormat dateFormat="yyyy-MM-dd'T'HH:mm:ss.SSSZZ"/></DataFormat></XMLElement><XMLElement comments="Last Modified On" dataType="datetime" isMappable="true" isNode="true" key="51" maxOccurs="1" minOccurs="0" name="lastModifiedOn" useNamespace="-1"><DataFormat><ProfileDateFormat dateFormat="yyyy-MM-dd'T'HH:mm:ss.SSSZZ"/></DataFormat></XMLElement><XMLElement comments="notes" dataType="character" isMappable="true" isNode="true" key="52" maxLength="4000" maxOccurs="1" minOccurs="0" name="notes" useNamespace="-1" validateData="true"><DataFormat><ProfileCharacterFormat/></DataFormat></XMLElement><XMLElement comments="operation" dataType="character" isMappable="true" isNode="true" key="53" maxOccurs="1" minOccurs="0" name="operation" useNamespace="-1"><DataFormat><ProfileCharacterFormat/></DataFormat></XMLElement><XMLElement comments="Province" dataType="character" isMappable="true" isNode="true" key="54" maxLength="256" maxOccurs="1" minOccurs="0" name="province" useNamespace="-1" validateData="true"><DataFormat><ProfileCharacterFormat/></DataFormat></XMLElement><XMLElement comments="State" dataType="character" isMappable="true" isNode="true" key="55" maxLength="256" maxOccurs="1" minOccurs="0" name="state" useNamespace="-1" validateData="true"><DataFormat><ProfileCharacterFormat/></DataFormat></XMLElement><XMLElement comments="Postal Code" dataType="character" isMappable="true" isNode="true" key="56" maxLength="256" maxOccurs="1" minOccurs="0" name="zipCode" useNamespace="-1" validateData="true"><DataFormat><ProfileCharacterFormat/></DataFormat></XMLElement></XMLElement></Type></Types></XMLNamespace></Namespaces></XMLProfile></bns:object></bns:Component>