<?xml version="1.0" encoding="UTF-8" standalone="yes"?><bns:Component xmlns:xsi="http://www.w3.org/2001/XMLSchema-instance" xmlns:bns="http://api.platform.boomi.com/" folderFullPath="JERA Co., Inc./TEST" componentId="b290b021-f87a-4f17-adad-71cd98f89d68" version="1" name="Disk v2 File CREATE Response" type="profile.json" createdDate="2024-06-17T08:28:32Z" createdBy="walid.bargaoui@avaxia-group.com" modifiedDate="2024-06-17T08:28:32Z" modifiedBy="walid.bargaoui@avaxia-group.com" deleted="false" currentVersion="true" folderName="TEST" folderId="RjoyOTk4NzM0" copiedFromComponentId="40be25fe-110f-44a0-9ab1-610929e5f1c2" copiedFromComponentVersion="1" branchName="main" branchId="QjozMzg0ODI"><bns:encryptedValues/><bns:object><JSONProfile xmlns="" strict="false"><GeneratorConfig enableFieldLengthValidation="true" enableParseDateTime="true"/><DataElements><JSONRootValue dataType="character" isMappable="true" isNode="true" key="1" name="File"><DataFormat><ProfileCharacterFormat/></DataFormat><JSONObject isMappable="false" isNode="true" key="2" name="Object"><JSONObjectEntry dataType="character" isMappable="true" isNode="true" key="3" name="createdDate" required="true"><DataFormat><ProfileCharacterFormat/></DataFormat></JSONObjectEntry><JSONObjectEntry dataType="character" isMappable="true" isNode="true" key="4" name="directory" required="true"><DataFormat><ProfileCharacterFormat/></DataFormat></JSONObjectEntry><JSONObjectEntry dataType="character" isMappable="true" isNode="true" key="5" name="fileName" required="true"><DataFormat><ProfileCharacterFormat/></DataFormat></JSONObjectEntry><JSONObjectEntry dataType="number" isMappable="true" isNode="true" key="6" name="fileSize" required="true"><DataFormat><ProfileNumberFormat/></DataFormat></JSONObjectEntry><JSONObjectEntry dataType="boolean" isMappable="true" isNode="true" key="7" name="isDirectory" required="true"><DataFormat/></JSONObjectEntry><JSONObjectEntry dataType="character" isMappable="true" isNode="true" key="8" name="modifiedDate" required="true"><DataFormat><ProfileCharacterFormat/></DataFormat></JSONObjectEntry></JSONObject></JSONRootValue></DataElements><tagLists/></JSONProfile></bns:object></bns:Component>