<?xml version="1.0" encoding="UTF-8" standalone="yes"?><bns:Component xmlns:xsi="http://www.w3.org/2001/XMLSchema-instance" xmlns:bns="http://api.platform.boomi.com/" folderFullPath="JERA Co., Inc./New HR - Interfaces /COMPANY_JUPITER" componentId="bd5b652b-b052-4b4f-9c3e-3f29b0c04501" version="1" name="conversion_reference_table" type="transform.map" createdDate="2021-01-07T03:34:50Z" createdBy="Daly.Fadhloun@avaxia-group.com" modifiedDate="2021-01-07T03:34:50Z" modifiedBy="Daly.Fadhloun@avaxia-group.com" deleted="false" currentVersion="true" folderName="COMPANY_JUPITER" folderId="RjozNjU5MzE3" branchName="main" branchId="QjozMzg0ODI"><bns:encryptedValues/><bns:description></bns:description><bns:object><Map xmlns=""><Mappings/><Functions optimizeExecutionOrder="true"/><Defaults/><DocumentCacheJoins/></Map></bns:object></bns:Component>